{
  "last_run": "2026-07-06 02:02:25 UTC",
  "mode": "Live 💰",
  "balance": 0.0282,
  "positions": [
    {
      "instId": "TRUMP-USDT-SWAP",
      "side": "شراء 📈",
      "entry": 1.693,
      "size": 58.0,
      "pnl": -0.0058
    }
  ],
  "total_trades": 241,
  "logs": [
    {
      "time": "2026-07-06 02:02:26 UTC",
      "msg": "مراكز مفتوحة: 1/1 — لا دخول جديد",
      "level": "info"
    },
    {
      "time": "2026-07-06 02:02:26 UTC",
      "msg": "📉 رأس المال الكلي: $0.36 | القمّة $10.66 | تراجع 96.7% | مُنظّم ×0.00",
      "level": "info"
    },
    {
      "time": "2026-07-06 02:02:26 UTC",
      "msg": "💰 الرصيد: $0.0282 USDT",
      "level": "info"
    },
    {
      "time": "2026-07-06 02:02:25 UTC",
      "msg": "⚙️ prime | رافعة x30 | مخاطرة 5% | مراكز 1 | مسح 300 عملة | أوامر taker",
      "level": "info"
    },
    {
      "time": "2026-07-06 02:02:10 UTC",
      "msg": "مراكز مفتوحة: 1/1 — لا دخول جديد",
      "level": "info"
    },
    {
      "time": "2026-07-06 02:02:10 UTC",
      "msg": "📉 رأس المال الكلي: $0.36 | القمّة $10.66 | تراجع 96.7% | مُنظّم ×0.00",
      "level": "info"
    },
    {
      "time": "2026-07-06 02:02:10 UTC",
      "msg": "💰 الرصيد: $0.0282 USDT",
      "level": "info"
    },
    {
      "time": "2026-07-06 02:02:09 UTC",
      "msg": "⚙️ prime | رافعة x30 | مخاطرة 5% | مراكز 1 | مسح 300 عملة | أوامر taker",
      "level": "info"
    },
    {
      "time": "2026-07-06 02:01:54 UTC",
      "msg": "مراكز مفتوحة: 1/1 — لا دخول جديد",
      "level": "info"
    },
    {
      "time": "2026-07-06 02:01:54 UTC",
      "msg": "📉 رأس المال الكلي: $0.36 | القمّة $10.66 | تراجع 96.6% | مُنظّم ×0.00",
      "level": "info"
    },
    {
      "time": "2026-07-06 02:01:54 UTC",
      "msg": "💰 الرصيد: $0.0338 USDT",
      "level": "info"
    },
    {
      "time": "2026-07-06 02:01:53 UTC",
      "msg": "⚙️ prime | رافعة x30 | مخاطرة 5% | مراكز 1 | مسح 300 عملة | أوامر taker",
      "level": "info"
    },
    {
      "time": "2026-07-06 02:01:38 UTC",
      "msg": "مراكز مفتوحة: 1/1 — لا دخول جديد",
      "level": "info"
    },
    {
      "time": "2026-07-06 02:01:38 UTC",
      "msg": "📉 رأس المال الكلي: $0.36 | القمّة $10.66 | تراجع 96.6% | مُنظّم ×0.00",
      "level": "info"
    },
    {
      "time": "2026-07-06 02:01:38 UTC",
      "msg": "💰 الرصيد: $0.0338 USDT",
      "level": "info"
    },
    {
      "time": "2026-07-06 02:01:38 UTC",
      "msg": "⚙️ prime | رافعة x30 | مخاطرة 5% | مراكز 1 | مسح 300 عملة | أوامر taker",
      "level": "info"
    },
    {
      "time": "2026-07-06 02:01:23 UTC",
      "msg": "مراكز مفتوحة: 1/1 — لا دخول جديد",
      "level": "info"
    },
    {
      "time": "2026-07-06 02:01:22 UTC",
      "msg": "📉 رأس المال الكلي: $0.37 | القمّة $10.66 | تراجع 96.5% | مُنظّم ×0.00",
      "level": "info"
    },
    {
      "time": "2026-07-06 02:01:22 UTC",
      "msg": "💰 الرصيد: $0.0394 USDT",
      "level": "info"
    },
    {
      "time": "2026-07-06 02:01:22 UTC",
      "msg": "⚙️ prime | رافعة x30 | مخاطرة 5% | مراكز 1 | مسح 300 عملة | أوامر taker",
      "level": "info"
    },
    {
      "time": "2026-07-06 02:01:07 UTC",
      "msg": "مراكز مفتوحة: 1/1 — لا دخول جديد",
      "level": "info"
    },
    {
      "time": "2026-07-06 02:01:06 UTC",
      "msg": "📉 رأس المال الكلي: $0.37 | القمّة $10.66 | تراجع 96.5% | مُنظّم ×0.00",
      "level": "info"
    },
    {
      "time": "2026-07-06 02:01:06 UTC",
      "msg": "💰 الرصيد: $0.0394 USDT",
      "level": "info"
    },
    {
      "time": "2026-07-06 02:01:06 UTC",
      "msg": "⚙️ prime | رافعة x30 | مخاطرة 5% | مراكز 1 | مسح 300 عملة | أوامر taker",
      "level": "info"
    },
    {
      "time": "2026-07-06 02:00:51 UTC",
      "msg": "مراكز مفتوحة: 1/1 — لا دخول جديد",
      "level": "info"
    },
    {
      "time": "2026-07-06 02:00:50 UTC",
      "msg": "📉 رأس المال الكلي: $0.37 | القمّة $10.66 | تراجع 96.5% | مُنظّم ×0.00",
      "level": "info"
    },
    {
      "time": "2026-07-06 02:00:50 UTC",
      "msg": "💰 الرصيد: $0.0394 USDT",
      "level": "info"
    },
    {
      "time": "2026-07-06 02:00:50 UTC",
      "msg": "⚙️ prime | رافعة x30 | مخاطرة 5% | مراكز 1 | مسح 300 عملة | أوامر taker",
      "level": "info"
    },
    {
      "time": "2026-07-06 02:00:35 UTC",
      "msg": "مراكز مفتوحة: 1/1 — لا دخول جديد",
      "level": "info"
    },
    {
      "time": "2026-07-06 02:00:35 UTC",
      "msg": "📉 رأس المال الكلي: $0.36 | القمّة $10.66 | تراجع 96.6% | مُنظّم ×0.00",
      "level": "info"
    },
    {
      "time": "2026-07-06 02:00:34 UTC",
      "msg": "💰 الرصيد: $0.0338 USDT",
      "level": "info"
    },
    {
      "time": "2026-07-06 02:00:34 UTC",
      "msg": "⚙️ prime | رافعة x30 | مخاطرة 5% | مراكز 1 | مسح 300 عملة | أوامر taker",
      "level": "info"
    },
    {
      "time": "2026-07-06 02:00:19 UTC",
      "msg": "مراكز مفتوحة: 1/1 — لا دخول جديد",
      "level": "info"
    },
    {
      "time": "2026-07-06 02:00:19 UTC",
      "msg": "📉 رأس المال الكلي: $0.36 | القمّة $10.66 | تراجع 96.6% | مُنظّم ×0.00",
      "level": "info"
    },
    {
      "time": "2026-07-06 02:00:18 UTC",
      "msg": "💰 الرصيد: $0.0338 USDT",
      "level": "info"
    },
    {
      "time": "2026-07-06 02:00:18 UTC",
      "msg": "⚙️ prime | رافعة x30 | مخاطرة 5% | مراكز 1 | مسح 300 عملة | أوامر taker",
      "level": "info"
    },
    {
      "time": "2026-07-06 02:00:03 UTC",
      "msg": "مراكز مفتوحة: 1/1 — لا دخول جديد",
      "level": "info"
    },
    {
      "time": "2026-07-06 02:00:03 UTC",
      "msg": "📉 رأس المال الكلي: $0.36 | القمّة $10.66 | تراجع 96.7% | مُنظّم ×0.00",
      "level": "info"
    },
    {
      "time": "2026-07-06 02:00:03 UTC",
      "msg": "💰 الرصيد: $0.0282 USDT",
      "level": "info"
    },
    {
      "time": "2026-07-06 02:00:02 UTC",
      "msg": "⚙️ prime | رافعة x30 | مخاطرة 5% | مراكز 1 | مسح 300 عملة | أوامر taker",
      "level": "info"
    },
    {
      "time": "2026-07-06 01:59:47 UTC",
      "msg": "مراكز مفتوحة: 1/1 — لا دخول جديد",
      "level": "info"
    },
    {
      "time": "2026-07-06 01:59:47 UTC",
      "msg": "📉 رأس المال الكلي: $0.36 | القمّة $10.66 | تراجع 96.7% | مُنظّم ×0.00",
      "level": "info"
    },
    {
      "time": "2026-07-06 01:59:47 UTC",
      "msg": "💰 الرصيد: $0.0282 USDT",
      "level": "info"
    },
    {
      "time": "2026-07-06 01:59:46 UTC",
      "msg": "⚙️ prime | رافعة x30 | مخاطرة 5% | مراكز 1 | مسح 300 عملة | أوامر taker",
      "level": "info"
    },
    {
      "time": "2026-07-06 01:59:31 UTC",
      "msg": "مراكز مفتوحة: 1/1 — لا دخول جديد",
      "level": "info"
    },
    {
      "time": "2026-07-06 01:59:31 UTC",
      "msg": "📉 رأس المال الكلي: $0.36 | القمّة $10.66 | تراجع 96.7% | مُنظّم ×0.00",
      "level": "info"
    },
    {
      "time": "2026-07-06 01:59:31 UTC",
      "msg": "💰 الرصيد: $0.0282 USDT",
      "level": "info"
    },
    {
      "time": "2026-07-06 01:59:31 UTC",
      "msg": "⚙️ prime | رافعة x30 | مخاطرة 5% | مراكز 1 | مسح 300 عملة | أوامر taker",
      "level": "info"
    },
    {
      "time": "2026-07-06 01:59:16 UTC",
      "msg": "مراكز مفتوحة: 1/1 — لا دخول جديد",
      "level": "info"
    },
    {
      "time": "2026-07-06 01:59:15 UTC",
      "msg": "📉 رأس المال الكلي: $0.36 | القمّة $10.66 | تراجع 96.7% | مُنظّم ×0.00",
      "level": "info"
    },
    {
      "time": "2026-07-06 01:59:15 UTC",
      "msg": "💰 الرصيد: $0.0282 USDT",
      "level": "info"
    },
    {
      "time": "2026-07-06 01:59:15 UTC",
      "msg": "⚙️ prime | رافعة x30 | مخاطرة 5% | مراكز 1 | مسح 300 عملة | أوامر taker",
      "level": "info"
    },
    {
      "time": "2026-07-06 01:59:00 UTC",
      "msg": "مراكز مفتوحة: 1/1 — لا دخول جديد",
      "level": "info"
    },
    {
      "time": "2026-07-06 01:58:59 UTC",
      "msg": "📉 رأس المال الكلي: $0.35 | القمّة $10.66 | تراجع 96.7% | مُنظّم ×0.00",
      "level": "info"
    },
    {
      "time": "2026-07-06 01:58:59 UTC",
      "msg": "💰 الرصيد: $0.0226 USDT",
      "level": "info"
    },
    {
      "time": "2026-07-06 01:58:59 UTC",
      "msg": "⚙️ prime | رافعة x30 | مخاطرة 5% | مراكز 1 | مسح 300 عملة | أوامر taker",
      "level": "info"
    },
    {
      "time": "2026-07-06 01:58:44 UTC",
      "msg": "مراكز مفتوحة: 1/1 — لا دخول جديد",
      "level": "info"
    },
    {
      "time": "2026-07-06 01:58:44 UTC",
      "msg": "📉 رأس المال الكلي: $0.35 | القمّة $10.66 | تراجع 96.7% | مُنظّم ×0.00",
      "level": "info"
    },
    {
      "time": "2026-07-06 01:58:43 UTC",
      "msg": "💰 الرصيد: $0.0226 USDT",
      "level": "info"
    },
    {
      "time": "2026-07-06 01:58:43 UTC",
      "msg": "⚙️ prime | رافعة x30 | مخاطرة 5% | مراكز 1 | مسح 300 عملة | أوامر taker",
      "level": "info"
    },
    {
      "time": "2026-07-06 01:58:28 UTC",
      "msg": "مراكز مفتوحة: 1/1 — لا دخول جديد",
      "level": "info"
    },
    {
      "time": "2026-07-06 01:58:28 UTC",
      "msg": "📉 رأس المال الكلي: $0.35 | القمّة $10.66 | تراجع 96.7% | مُنظّم ×0.00",
      "level": "info"
    },
    {
      "time": "2026-07-06 01:58:27 UTC",
      "msg": "💰 الرصيد: $0.0226 USDT",
      "level": "info"
    },
    {
      "time": "2026-07-06 01:58:27 UTC",
      "msg": "⚙️ prime | رافعة x30 | مخاطرة 5% | مراكز 1 | مسح 300 عملة | أوامر taker",
      "level": "info"
    },
    {
      "time": "2026-07-06 01:58:12 UTC",
      "msg": "مراكز مفتوحة: 1/1 — لا دخول جديد",
      "level": "info"
    },
    {
      "time": "2026-07-06 01:58:12 UTC",
      "msg": "📉 رأس المال الكلي: $0.36 | القمّة $10.66 | تراجع 96.7% | مُنظّم ×0.00",
      "level": "info"
    },
    {
      "time": "2026-07-06 01:58:12 UTC",
      "msg": "💰 الرصيد: $0.0282 USDT",
      "level": "info"
    },
    {
      "time": "2026-07-06 01:58:11 UTC",
      "msg": "⚙️ prime | رافعة x30 | مخاطرة 5% | مراكز 1 | مسح 300 عملة | أوامر taker",
      "level": "info"
    },
    {
      "time": "2026-07-06 01:57:56 UTC",
      "msg": "مراكز مفتوحة: 1/1 — لا دخول جديد",
      "level": "info"
    },
    {
      "time": "2026-07-06 01:57:56 UTC",
      "msg": "📉 رأس المال الكلي: $0.35 | القمّة $10.66 | تراجع 96.7% | مُنظّم ×0.00",
      "level": "info"
    },
    {
      "time": "2026-07-06 01:57:56 UTC",
      "msg": "💰 الرصيد: $0.0226 USDT",
      "level": "info"
    },
    {
      "time": "2026-07-06 01:57:55 UTC",
      "msg": "⚙️ prime | رافعة x30 | مخاطرة 5% | مراكز 1 | مسح 300 عملة | أوامر taker",
      "level": "info"
    },
    {
      "time": "2026-07-06 01:57:40 UTC",
      "msg": "مراكز مفتوحة: 1/1 — لا دخول جديد",
      "level": "info"
    },
    {
      "time": "2026-07-06 01:57:40 UTC",
      "msg": "📉 رأس المال الكلي: $0.36 | القمّة $10.66 | تراجع 96.7% | مُنظّم ×0.00",
      "level": "info"
    },
    {
      "time": "2026-07-06 01:57:40 UTC",
      "msg": "💰 الرصيد: $0.0282 USDT",
      "level": "info"
    },
    {
      "time": "2026-07-06 01:57:40 UTC",
      "msg": "⚙️ prime | رافعة x30 | مخاطرة 5% | مراكز 1 | مسح 300 عملة | أوامر taker",
      "level": "info"
    },
    {
      "time": "2026-07-06 01:57:25 UTC",
      "msg": "مراكز مفتوحة: 1/1 — لا دخول جديد",
      "level": "info"
    },
    {
      "time": "2026-07-06 01:57:24 UTC",
      "msg": "📉 رأس المال الكلي: $0.36 | القمّة $10.66 | تراجع 96.7% | مُنظّم ×0.00",
      "level": "info"
    },
    {
      "time": "2026-07-06 01:57:24 UTC",
      "msg": "💰 الرصيد: $0.0282 USDT",
      "level": "info"
    },
    {
      "time": "2026-07-06 01:57:24 UTC",
      "msg": "⚙️ prime | رافعة x30 | مخاطرة 5% | مراكز 1 | مسح 300 عملة | أوامر taker",
      "level": "info"
    }
  ],
  "risk_mode": "prime",
  "top_signals": [
    {
      "instId": "ARX-USDT-SWAP",
      "signal": "buy",
      "score": 39,
      "prob": 0.62
    },
    {
      "instId": "TRUMP-USDT-SWAP",
      "signal": "sell",
      "score": -45,
      "prob": 0.31
    },
    {
      "instId": "GIGGLE-USDT-SWAP",
      "signal": "buy",
      "score": 38,
      "prob": 0.63
    }
  ],
  "peaks": {},
  "equity_peak": 10.6567,
  "drawdown": 96.65,
  "brain_stats": {
    "wins": 32,
    "losses": 66,
    "total_closed": 98,
    "win_rate": 32.7,
    "weights": {
      "EMA": 0.78,
      "RSI": 1.09,
      "MACD": 0.777,
      "BB": 1.042,
      "Stoch": 1.021,
      "Volume": 0.983,
      "Pattern": 0.873,
      "HTF_1h": 0.749,
      "OBV": 0.877,
      "RSIDivergence": 0.964
    },
    "kelly": 5.1,
    "updated": "2026-07-06 02:02:10 UTC"
  }
}