{
  "last_run": "2026-06-28 05:38:52 UTC",
  "mode": "Live 💰",
  "balance": 0.0603,
  "positions": [
    {
      "instId": "SAMSUNG-USDT-SWAP",
      "side": "شراء 📈",
      "entry": 223.48,
      "size": 0.09,
      "pnl": -0.0234
    }
  ],
  "total_trades": 170,
  "logs": [
    {
      "time": "2026-06-28 05:38:53 UTC",
      "msg": "مراكز مفتوحة: 1/1 — لا دخول جديد",
      "level": "info"
    },
    {
      "time": "2026-06-28 05:38:52 UTC",
      "msg": "📉 رأس المال الكلي: $1.06 | القمّة $13.21 | تراجع 91.9% | مُنظّم ×0.00",
      "level": "info"
    },
    {
      "time": "2026-06-28 05:38:52 UTC",
      "msg": "💰 الرصيد: $0.0603 USDT",
      "level": "info"
    },
    {
      "time": "2026-06-28 05:38:52 UTC",
      "msg": "⚙️ rocket | رافعة أقصى/عملة | مخاطرة 5% | مراكز 1 | مسح 100 عملة | أوامر taker",
      "level": "info"
    },
    {
      "time": "2026-06-28 05:38:52 UTC",
      "msg": "الوضع: Live 💰",
      "level": "info"
    },
    {
      "time": "2026-06-28 05:38:52 UTC",
      "msg": "🚀 تشغيل Snowball v22 + Brain...",
      "level": "success"
    },
    {
      "time": "2026-06-28 05:38:48 UTC",
      "msg": "مراكز مفتوحة: 1/1 — لا دخول جديد",
      "level": "info"
    },
    {
      "time": "2026-06-28 05:38:48 UTC",
      "msg": "📉 رأس المال الكلي: $1.06 | القمّة $13.21 | تراجع 91.9% | مُنظّم ×0.00",
      "level": "info"
    },
    {
      "time": "2026-06-28 05:38:48 UTC",
      "msg": "💰 الرصيد: $0.0603 USDT",
      "level": "info"
    },
    {
      "time": "2026-06-28 05:38:47 UTC",
      "msg": "⚙️ rocket | رافعة أقصى/عملة | مخاطرة 5% | مراكز 1 | مسح 100 عملة | أوامر taker",
      "level": "info"
    },
    {
      "time": "2026-06-28 05:38:47 UTC",
      "msg": "الوضع: Live 💰",
      "level": "info"
    },
    {
      "time": "2026-06-28 05:38:47 UTC",
      "msg": "🚀 تشغيل Snowball v22 + Brain...",
      "level": "success"
    },
    {
      "time": "2026-06-28 05:38:43 UTC",
      "msg": "مراكز مفتوحة: 1/1 — لا دخول جديد",
      "level": "info"
    },
    {
      "time": "2026-06-28 05:38:43 UTC",
      "msg": "📉 رأس المال الكلي: $1.06 | القمّة $13.21 | تراجع 91.9% | مُنظّم ×0.00",
      "level": "info"
    },
    {
      "time": "2026-06-28 05:38:43 UTC",
      "msg": "💰 الرصيد: $0.0594 USDT",
      "level": "info"
    },
    {
      "time": "2026-06-28 05:38:42 UTC",
      "msg": "⚙️ rocket | رافعة أقصى/عملة | مخاطرة 5% | مراكز 1 | مسح 100 عملة | أوامر taker",
      "level": "info"
    },
    {
      "time": "2026-06-28 05:38:42 UTC",
      "msg": "الوضع: Live 💰",
      "level": "info"
    },
    {
      "time": "2026-06-28 05:38:42 UTC",
      "msg": "🚀 تشغيل Snowball v22 + Brain...",
      "level": "success"
    },
    {
      "time": "2026-06-28 05:38:39 UTC",
      "msg": "مراكز مفتوحة: 1/1 — لا دخول جديد",
      "level": "info"
    },
    {
      "time": "2026-06-28 05:38:38 UTC",
      "msg": "📉 رأس المال الكلي: $1.06 | القمّة $13.21 | تراجع 91.9% | مُنظّم ×0.00",
      "level": "info"
    },
    {
      "time": "2026-06-28 05:38:38 UTC",
      "msg": "💰 الرصيد: $0.0594 USDT",
      "level": "info"
    },
    {
      "time": "2026-06-28 05:38:38 UTC",
      "msg": "⚙️ rocket | رافعة أقصى/عملة | مخاطرة 5% | مراكز 1 | مسح 100 عملة | أوامر taker",
      "level": "info"
    },
    {
      "time": "2026-06-28 05:38:38 UTC",
      "msg": "الوضع: Live 💰",
      "level": "info"
    },
    {
      "time": "2026-06-28 05:38:38 UTC",
      "msg": "🚀 تشغيل Snowball v22 + Brain...",
      "level": "success"
    },
    {
      "time": "2026-06-28 05:38:33 UTC",
      "msg": "مراكز مفتوحة: 1/1 — لا دخول جديد",
      "level": "info"
    },
    {
      "time": "2026-06-28 05:38:33 UTC",
      "msg": "📉 رأس المال الكلي: $1.06 | القمّة $13.21 | تراجع 91.9% | مُنظّم ×0.00",
      "level": "info"
    },
    {
      "time": "2026-06-28 05:38:32 UTC",
      "msg": "💰 الرصيد: $0.0594 USDT",
      "level": "info"
    },
    {
      "time": "2026-06-28 05:38:32 UTC",
      "msg": "⚙️ rocket | رافعة أقصى/عملة | مخاطرة 5% | مراكز 1 | مسح 100 عملة | أوامر taker",
      "level": "info"
    },
    {
      "time": "2026-06-28 05:38:32 UTC",
      "msg": "الوضع: Live 💰",
      "level": "info"
    },
    {
      "time": "2026-06-28 05:38:32 UTC",
      "msg": "🚀 تشغيل Snowball v22 + Brain...",
      "level": "success"
    },
    {
      "time": "2026-06-28 05:38:30 UTC",
      "msg": "مراكز مفتوحة: 1/1 — لا دخول جديد",
      "level": "info"
    },
    {
      "time": "2026-06-28 05:38:30 UTC",
      "msg": "📉 رأس المال الكلي: $1.06 | القمّة $13.21 | تراجع 91.9% | مُنظّم ×0.00",
      "level": "info"
    },
    {
      "time": "2026-06-28 05:38:30 UTC",
      "msg": "💰 الرصيد: $0.0594 USDT",
      "level": "info"
    },
    {
      "time": "2026-06-28 05:38:29 UTC",
      "msg": "⚙️ rocket | رافعة أقصى/عملة | مخاطرة 5% | مراكز 1 | مسح 100 عملة | أوامر taker",
      "level": "info"
    },
    {
      "time": "2026-06-28 05:38:29 UTC",
      "msg": "الوضع: Live 💰",
      "level": "info"
    },
    {
      "time": "2026-06-28 05:38:29 UTC",
      "msg": "🚀 تشغيل Snowball v22 + Brain...",
      "level": "success"
    },
    {
      "time": "2026-06-28 05:38:21 UTC",
      "msg": "مراكز مفتوحة: 1/1 — لا دخول جديد",
      "level": "info"
    },
    {
      "time": "2026-06-28 05:38:21 UTC",
      "msg": "📉 رأس المال الكلي: $1.06 | القمّة $13.21 | تراجع 92.0% | مُنظّم ×0.00",
      "level": "info"
    },
    {
      "time": "2026-06-28 05:38:21 UTC",
      "msg": "💰 الرصيد: $0.0586 USDT",
      "level": "info"
    },
    {
      "time": "2026-06-28 05:38:20 UTC",
      "msg": "⚙️ rocket | رافعة أقصى/عملة | مخاطرة 5% | مراكز 1 | مسح 100 عملة | أوامر taker",
      "level": "info"
    },
    {
      "time": "2026-06-28 05:38:20 UTC",
      "msg": "الوضع: Live 💰",
      "level": "info"
    },
    {
      "time": "2026-06-28 05:38:20 UTC",
      "msg": "🚀 تشغيل Snowball v22 + Brain...",
      "level": "success"
    },
    {
      "time": "2026-06-28 05:38:18 UTC",
      "msg": "مراكز مفتوحة: 1/1 — لا دخول جديد",
      "level": "info"
    },
    {
      "time": "2026-06-28 05:38:17 UTC",
      "msg": "📉 رأس المال الكلي: $1.06 | القمّة $13.21 | تراجع 92.0% | مُنظّم ×0.00",
      "level": "info"
    },
    {
      "time": "2026-06-28 05:38:17 UTC",
      "msg": "💰 الرصيد: $0.0586 USDT",
      "level": "info"
    },
    {
      "time": "2026-06-28 05:38:17 UTC",
      "msg": "⚙️ rocket | رافعة أقصى/عملة | مخاطرة 5% | مراكز 1 | مسح 100 عملة | أوامر taker",
      "level": "info"
    },
    {
      "time": "2026-06-28 05:38:17 UTC",
      "msg": "الوضع: Live 💰",
      "level": "info"
    },
    {
      "time": "2026-06-28 05:38:17 UTC",
      "msg": "🚀 تشغيل Snowball v22 + Brain...",
      "level": "success"
    },
    {
      "time": "2026-06-28 05:38:10 UTC",
      "msg": "مراكز مفتوحة: 1/1 — لا دخول جديد",
      "level": "info"
    },
    {
      "time": "2026-06-28 05:38:10 UTC",
      "msg": "📉 رأس المال الكلي: $1.06 | القمّة $13.21 | تراجع 92.0% | مُنظّم ×0.00",
      "level": "info"
    },
    {
      "time": "2026-06-28 05:38:10 UTC",
      "msg": "💰 الرصيد: $0.0577 USDT",
      "level": "info"
    },
    {
      "time": "2026-06-28 05:38:09 UTC",
      "msg": "⚙️ rocket | رافعة أقصى/عملة | مخاطرة 5% | مراكز 1 | مسح 100 عملة | أوامر taker",
      "level": "info"
    },
    {
      "time": "2026-06-28 05:38:09 UTC",
      "msg": "الوضع: Live 💰",
      "level": "info"
    },
    {
      "time": "2026-06-28 05:38:09 UTC",
      "msg": "🚀 تشغيل Snowball v22 + Brain...",
      "level": "success"
    },
    {
      "time": "2026-06-28 05:37:34 UTC",
      "msg": "مراكز مفتوحة: 1/1 — لا دخول جديد",
      "level": "info"
    },
    {
      "time": "2026-06-28 05:37:34 UTC",
      "msg": "📉 رأس المال الكلي: $1.06 | القمّة $13.21 | تراجع 92.0% | مُنظّم ×0.00",
      "level": "info"
    },
    {
      "time": "2026-06-28 05:37:33 UTC",
      "msg": "💰 الرصيد: $0.0518 USDT",
      "level": "info"
    },
    {
      "time": "2026-06-28 05:37:33 UTC",
      "msg": "⚙️ rocket | رافعة أقصى/عملة | مخاطرة 5% | مراكز 1 | مسح 100 عملة | أوامر taker",
      "level": "info"
    },
    {
      "time": "2026-06-28 05:37:33 UTC",
      "msg": "الوضع: Live 💰",
      "level": "info"
    },
    {
      "time": "2026-06-28 05:37:33 UTC",
      "msg": "🚀 تشغيل Snowball v22 + Brain...",
      "level": "success"
    },
    {
      "time": "2026-06-28 05:37:29 UTC",
      "msg": "مراكز مفتوحة: 1/1 — لا دخول جديد",
      "level": "info"
    },
    {
      "time": "2026-06-28 05:37:28 UTC",
      "msg": "📉 رأس المال الكلي: $1.06 | القمّة $13.21 | تراجع 92.0% | مُنظّم ×0.00",
      "level": "info"
    },
    {
      "time": "2026-06-28 05:37:28 UTC",
      "msg": "💰 الرصيد: $0.0518 USDT",
      "level": "info"
    },
    {
      "time": "2026-06-28 05:37:28 UTC",
      "msg": "⚙️ rocket | رافعة أقصى/عملة | مخاطرة 5% | مراكز 1 | مسح 100 عملة | أوامر taker",
      "level": "info"
    },
    {
      "time": "2026-06-28 05:37:28 UTC",
      "msg": "الوضع: Live 💰",
      "level": "info"
    },
    {
      "time": "2026-06-28 05:37:28 UTC",
      "msg": "🚀 تشغيل Snowball v22 + Brain...",
      "level": "success"
    },
    {
      "time": "2026-06-28 05:37:23 UTC",
      "msg": "مراكز مفتوحة: 1/1 — لا دخول جديد",
      "level": "info"
    },
    {
      "time": "2026-06-28 05:37:23 UTC",
      "msg": "📉 رأس المال الكلي: $1.06 | القمّة $13.21 | تراجع 92.0% | مُنظّم ×0.00",
      "level": "info"
    },
    {
      "time": "2026-06-28 05:37:23 UTC",
      "msg": "💰 الرصيد: $0.0518 USDT",
      "level": "info"
    },
    {
      "time": "2026-06-28 05:37:22 UTC",
      "msg": "⚙️ rocket | رافعة أقصى/عملة | مخاطرة 5% | مراكز 1 | مسح 100 عملة | أوامر taker",
      "level": "info"
    },
    {
      "time": "2026-06-28 05:37:22 UTC",
      "msg": "الوضع: Live 💰",
      "level": "info"
    },
    {
      "time": "2026-06-28 05:37:22 UTC",
      "msg": "🚀 تشغيل Snowball v22 + Brain...",
      "level": "success"
    },
    {
      "time": "2026-06-28 05:37:14 UTC",
      "msg": "مراكز مفتوحة: 1/1 — لا دخول جديد",
      "level": "info"
    },
    {
      "time": "2026-06-28 05:37:14 UTC",
      "msg": "📉 رأس المال الكلي: $1.06 | القمّة $13.21 | تراجع 92.0% | مُنظّم ×0.00",
      "level": "info"
    },
    {
      "time": "2026-06-28 05:37:14 UTC",
      "msg": "💰 الرصيد: $0.0518 USDT",
      "level": "info"
    },
    {
      "time": "2026-06-28 05:37:13 UTC",
      "msg": "⚙️ rocket | رافعة أقصى/عملة | مخاطرة 5% | مراكز 1 | مسح 100 عملة | أوامر taker",
      "level": "info"
    },
    {
      "time": "2026-06-28 05:37:13 UTC",
      "msg": "الوضع: Live 💰",
      "level": "info"
    },
    {
      "time": "2026-06-28 05:37:13 UTC",
      "msg": "🚀 تشغيل Snowball v22 + Brain...",
      "level": "success"
    },
    {
      "time": "2026-06-28 05:37:09 UTC",
      "msg": "مراكز مفتوحة: 1/1 — لا دخول جديد",
      "level": "info"
    },
    {
      "time": "2026-06-28 05:37:09 UTC",
      "msg": "📉 رأس المال الكلي: $1.06 | القمّة $13.21 | تراجع 92.0% | مُنظّم ×0.00",
      "level": "info"
    }
  ],
  "risk_mode": "rocket",
  "top_signals": [
    {
      "instId": "SAMSUNG-USDT-SWAP",
      "signal": "buy",
      "score": 36,
      "prob": 0.71
    },
    {
      "instId": "AAVE-USDT-SWAP",
      "signal": "buy",
      "score": 45,
      "prob": 0.69
    },
    {
      "instId": "PEPE-USDT-SWAP",
      "signal": "sell",
      "score": -36,
      "prob": 0.31
    }
  ],
  "peaks": {
    "DOT-USDT-SWAP": -0.0149326962049612
  },
  "pnl_peaks": {
    "DOT-USDT-SWAP": -0.0419999999999945
  },
  "brain_stats": {
    "wins": 17,
    "losses": 38,
    "total_closed": 55,
    "win_rate": 30.9,
    "weights": {
      "EMA": 0.787,
      "RSI": 1.045,
      "MACD": 0.834,
      "BB": 1.029,
      "Stoch": 0.996,
      "Volume": 0.981,
      "Pattern": 0.898,
      "HTF_1h": 0.757,
      "OBV": 0.852,
      "RSIDivergence": 0.994
    },
    "kelly": 5.0,
    "updated": "2026-06-28 05:38:48 UTC"
  },
  "equity_peak": 13.2074,
  "drawdown": 91.94
}