{
  "last_run": "2026-07-06 12:29:45 UTC",
  "mode": "Live 💰",
  "balance": 0.006,
  "positions": [
    {
      "instId": "1000000MOG_USDT",
      "side": "شراء 📈",
      "entry": 0.1141,
      "size": 12.0,
      "pnl": 0.0
    }
  ],
  "total_trades": 243,
  "logs": [
    {
      "time": "2026-07-06 12:29:46 UTC",
      "msg": "مراكز مفتوحة: 1/1 — لا دخول جديد",
      "level": "info"
    },
    {
      "time": "2026-07-06 12:29:45 UTC",
      "msg": "📉 رأس المال الكلي: $0.13 | القمّة $10.66 | تراجع 98.8% | مُنظّم ×0.00",
      "level": "info"
    },
    {
      "time": "2026-07-06 12:29:45 UTC",
      "msg": "💰 الرصيد: $0.0060 USDT",
      "level": "info"
    },
    {
      "time": "2026-07-06 12:29:45 UTC",
      "msg": "⚙️ prime | رافعة x50 | مخاطرة 5% | مراكز 1 | مسح 300 عملة | أوامر taker",
      "level": "info"
    },
    {
      "time": "2026-07-06 12:29:30 UTC",
      "msg": "مراكز مفتوحة: 1/1 — لا دخول جديد",
      "level": "info"
    },
    {
      "time": "2026-07-06 12:29:30 UTC",
      "msg": "📉 رأس المال الكلي: $0.13 | القمّة $10.66 | تراجع 98.8% | مُنظّم ×0.00",
      "level": "info"
    },
    {
      "time": "2026-07-06 12:29:30 UTC",
      "msg": "💰 الرصيد: $0.0060 USDT",
      "level": "info"
    },
    {
      "time": "2026-07-06 12:29:30 UTC",
      "msg": "⚙️ prime | رافعة x50 | مخاطرة 5% | مراكز 1 | مسح 300 عملة | أوامر taker",
      "level": "info"
    },
    {
      "time": "2026-07-06 12:29:14 UTC",
      "msg": "مراكز مفتوحة: 1/1 — لا دخول جديد",
      "level": "info"
    },
    {
      "time": "2026-07-06 12:29:14 UTC",
      "msg": "📉 رأس المال الكلي: $0.13 | القمّة $10.66 | تراجع 98.8% | مُنظّم ×0.00",
      "level": "info"
    },
    {
      "time": "2026-07-06 12:29:14 UTC",
      "msg": "💰 الرصيد: $0.0060 USDT",
      "level": "info"
    },
    {
      "time": "2026-07-06 12:29:14 UTC",
      "msg": "⚙️ prime | رافعة x50 | مخاطرة 5% | مراكز 1 | مسح 300 عملة | أوامر taker",
      "level": "info"
    },
    {
      "time": "2026-07-06 12:28:59 UTC",
      "msg": "مراكز مفتوحة: 1/1 — لا دخول جديد",
      "level": "info"
    },
    {
      "time": "2026-07-06 12:28:59 UTC",
      "msg": "📉 رأس المال الكلي: $0.13 | القمّة $10.66 | تراجع 98.8% | مُنظّم ×0.00",
      "level": "info"
    },
    {
      "time": "2026-07-06 12:28:59 UTC",
      "msg": "💰 الرصيد: $0.0060 USDT",
      "level": "info"
    },
    {
      "time": "2026-07-06 12:28:58 UTC",
      "msg": "⚙️ prime | رافعة x50 | مخاطرة 5% | مراكز 1 | مسح 300 عملة | أوامر taker",
      "level": "info"
    },
    {
      "time": "2026-07-06 12:28:43 UTC",
      "msg": "مراكز مفتوحة: 1/1 — لا دخول جديد",
      "level": "info"
    },
    {
      "time": "2026-07-06 12:28:43 UTC",
      "msg": "📉 رأس المال الكلي: $0.13 | القمّة $10.66 | تراجع 98.8% | مُنظّم ×0.00",
      "level": "info"
    },
    {
      "time": "2026-07-06 12:28:43 UTC",
      "msg": "💰 الرصيد: $0.0060 USDT",
      "level": "info"
    },
    {
      "time": "2026-07-06 12:28:43 UTC",
      "msg": "⚙️ prime | رافعة x50 | مخاطرة 5% | مراكز 1 | مسح 300 عملة | أوامر taker",
      "level": "info"
    },
    {
      "time": "2026-07-06 12:28:28 UTC",
      "msg": "مراكز مفتوحة: 1/1 — لا دخول جديد",
      "level": "info"
    },
    {
      "time": "2026-07-06 12:28:28 UTC",
      "msg": "📉 رأس المال الكلي: $0.13 | القمّة $10.66 | تراجع 98.8% | مُنظّم ×0.00",
      "level": "info"
    },
    {
      "time": "2026-07-06 12:28:28 UTC",
      "msg": "💰 الرصيد: $0.0060 USDT",
      "level": "info"
    },
    {
      "time": "2026-07-06 12:28:27 UTC",
      "msg": "⚙️ prime | رافعة x50 | مخاطرة 5% | مراكز 1 | مسح 300 عملة | أوامر taker",
      "level": "info"
    },
    {
      "time": "2026-07-06 12:28:12 UTC",
      "msg": "مراكز مفتوحة: 1/1 — لا دخول جديد",
      "level": "info"
    },
    {
      "time": "2026-07-06 12:28:12 UTC",
      "msg": "📉 رأس المال الكلي: $0.13 | القمّة $10.66 | تراجع 98.8% | مُنظّم ×0.00",
      "level": "info"
    },
    {
      "time": "2026-07-06 12:28:12 UTC",
      "msg": "💰 الرصيد: $0.0060 USDT",
      "level": "info"
    },
    {
      "time": "2026-07-06 12:28:12 UTC",
      "msg": "⚙️ prime | رافعة x50 | مخاطرة 5% | مراكز 1 | مسح 300 عملة | أوامر taker",
      "level": "info"
    },
    {
      "time": "2026-07-06 12:27:57 UTC",
      "msg": "مراكز مفتوحة: 1/1 — لا دخول جديد",
      "level": "info"
    },
    {
      "time": "2026-07-06 12:27:57 UTC",
      "msg": "📉 رأس المال الكلي: $0.13 | القمّة $10.66 | تراجع 98.8% | مُنظّم ×0.00",
      "level": "info"
    },
    {
      "time": "2026-07-06 12:27:57 UTC",
      "msg": "💰 الرصيد: $0.0060 USDT",
      "level": "info"
    },
    {
      "time": "2026-07-06 12:27:56 UTC",
      "msg": "⚙️ prime | رافعة x50 | مخاطرة 5% | مراكز 1 | مسح 300 عملة | أوامر taker",
      "level": "info"
    },
    {
      "time": "2026-07-06 12:27:41 UTC",
      "msg": "مراكز مفتوحة: 1/1 — لا دخول جديد",
      "level": "info"
    },
    {
      "time": "2026-07-06 12:27:41 UTC",
      "msg": "📉 رأس المال الكلي: $0.13 | القمّة $10.66 | تراجع 98.8% | مُنظّم ×0.00",
      "level": "info"
    },
    {
      "time": "2026-07-06 12:27:41 UTC",
      "msg": "💰 الرصيد: $0.0060 USDT",
      "level": "info"
    },
    {
      "time": "2026-07-06 12:27:41 UTC",
      "msg": "⚙️ prime | رافعة x50 | مخاطرة 5% | مراكز 1 | مسح 300 عملة | أوامر taker",
      "level": "info"
    },
    {
      "time": "2026-07-06 12:27:26 UTC",
      "msg": "مراكز مفتوحة: 1/1 — لا دخول جديد",
      "level": "info"
    },
    {
      "time": "2026-07-06 12:27:26 UTC",
      "msg": "📉 رأس المال الكلي: $0.13 | القمّة $10.66 | تراجع 98.8% | مُنظّم ×0.00",
      "level": "info"
    },
    {
      "time": "2026-07-06 12:27:25 UTC",
      "msg": "💰 الرصيد: $0.0060 USDT",
      "level": "info"
    },
    {
      "time": "2026-07-06 12:27:25 UTC",
      "msg": "⚙️ prime | رافعة x50 | مخاطرة 5% | مراكز 1 | مسح 300 عملة | أوامر taker",
      "level": "info"
    },
    {
      "time": "2026-07-06 12:27:10 UTC",
      "msg": "مراكز مفتوحة: 1/1 — لا دخول جديد",
      "level": "info"
    },
    {
      "time": "2026-07-06 12:27:10 UTC",
      "msg": "📉 رأس المال الكلي: $0.13 | القمّة $10.66 | تراجع 98.8% | مُنظّم ×0.00",
      "level": "info"
    },
    {
      "time": "2026-07-06 12:27:10 UTC",
      "msg": "💰 الرصيد: $0.0060 USDT",
      "level": "info"
    },
    {
      "time": "2026-07-06 12:27:10 UTC",
      "msg": "⚙️ prime | رافعة x50 | مخاطرة 5% | مراكز 1 | مسح 300 عملة | أوامر taker",
      "level": "info"
    },
    {
      "time": "2026-07-06 12:26:55 UTC",
      "msg": "مراكز مفتوحة: 1/1 — لا دخول جديد",
      "level": "info"
    },
    {
      "time": "2026-07-06 12:26:55 UTC",
      "msg": "📉 رأس المال الكلي: $0.13 | القمّة $10.66 | تراجع 98.8% | مُنظّم ×0.00",
      "level": "info"
    },
    {
      "time": "2026-07-06 12:26:54 UTC",
      "msg": "💰 الرصيد: $0.0060 USDT",
      "level": "info"
    },
    {
      "time": "2026-07-06 12:26:54 UTC",
      "msg": "⚙️ prime | رافعة x50 | مخاطرة 5% | مراكز 1 | مسح 300 عملة | أوامر taker",
      "level": "info"
    },
    {
      "time": "2026-07-06 12:26:39 UTC",
      "msg": "مراكز مفتوحة: 1/1 — لا دخول جديد",
      "level": "info"
    },
    {
      "time": "2026-07-06 12:26:39 UTC",
      "msg": "📉 رأس المال الكلي: $0.13 | القمّة $10.66 | تراجع 98.8% | مُنظّم ×0.00",
      "level": "info"
    },
    {
      "time": "2026-07-06 12:26:39 UTC",
      "msg": "💰 الرصيد: $0.0060 USDT",
      "level": "info"
    },
    {
      "time": "2026-07-06 12:26:39 UTC",
      "msg": "⚙️ prime | رافعة x50 | مخاطرة 5% | مراكز 1 | مسح 300 عملة | أوامر taker",
      "level": "info"
    },
    {
      "time": "2026-07-06 12:26:24 UTC",
      "msg": "مراكز مفتوحة: 1/1 — لا دخول جديد",
      "level": "info"
    },
    {
      "time": "2026-07-06 12:26:24 UTC",
      "msg": "📉 رأس المال الكلي: $0.13 | القمّة $10.66 | تراجع 98.8% | مُنظّم ×0.00",
      "level": "info"
    },
    {
      "time": "2026-07-06 12:26:23 UTC",
      "msg": "💰 الرصيد: $0.0060 USDT",
      "level": "info"
    },
    {
      "time": "2026-07-06 12:26:23 UTC",
      "msg": "⚙️ prime | رافعة x50 | مخاطرة 5% | مراكز 1 | مسح 300 عملة | أوامر taker",
      "level": "info"
    },
    {
      "time": "2026-07-06 12:26:08 UTC",
      "msg": "مراكز مفتوحة: 1/1 — لا دخول جديد",
      "level": "info"
    },
    {
      "time": "2026-07-06 12:26:08 UTC",
      "msg": "📉 رأس المال الكلي: $0.13 | القمّة $10.66 | تراجع 98.8% | مُنظّم ×0.00",
      "level": "info"
    },
    {
      "time": "2026-07-06 12:26:08 UTC",
      "msg": "💰 الرصيد: $0.0060 USDT",
      "level": "info"
    },
    {
      "time": "2026-07-06 12:26:08 UTC",
      "msg": "⚙️ prime | رافعة x50 | مخاطرة 5% | مراكز 1 | مسح 300 عملة | أوامر taker",
      "level": "info"
    },
    {
      "time": "2026-07-06 12:25:52 UTC",
      "msg": "مراكز مفتوحة: 1/1 — لا دخول جديد",
      "level": "info"
    },
    {
      "time": "2026-07-06 12:25:52 UTC",
      "msg": "📉 رأس المال الكلي: $0.13 | القمّة $10.66 | تراجع 98.8% | مُنظّم ×0.00",
      "level": "info"
    },
    {
      "time": "2026-07-06 12:25:52 UTC",
      "msg": "💰 الرصيد: $0.0060 USDT",
      "level": "info"
    },
    {
      "time": "2026-07-06 12:25:52 UTC",
      "msg": "⚙️ prime | رافعة x50 | مخاطرة 5% | مراكز 1 | مسح 300 عملة | أوامر taker",
      "level": "info"
    },
    {
      "time": "2026-07-06 12:25:37 UTC",
      "msg": "مراكز مفتوحة: 1/1 — لا دخول جديد",
      "level": "info"
    },
    {
      "time": "2026-07-06 12:25:36 UTC",
      "msg": "📉 رأس المال الكلي: $0.13 | القمّة $10.66 | تراجع 98.8% | مُنظّم ×0.00",
      "level": "info"
    },
    {
      "time": "2026-07-06 12:25:36 UTC",
      "msg": "💰 الرصيد: $0.0060 USDT",
      "level": "info"
    },
    {
      "time": "2026-07-06 12:25:36 UTC",
      "msg": "⚙️ prime | رافعة x50 | مخاطرة 5% | مراكز 1 | مسح 300 عملة | أوامر taker",
      "level": "info"
    },
    {
      "time": "2026-07-06 12:25:21 UTC",
      "msg": "مراكز مفتوحة: 1/1 — لا دخول جديد",
      "level": "info"
    },
    {
      "time": "2026-07-06 12:25:21 UTC",
      "msg": "📉 رأس المال الكلي: $0.13 | القمّة $10.66 | تراجع 98.8% | مُنظّم ×0.00",
      "level": "info"
    },
    {
      "time": "2026-07-06 12:25:21 UTC",
      "msg": "💰 الرصيد: $0.0060 USDT",
      "level": "info"
    },
    {
      "time": "2026-07-06 12:25:20 UTC",
      "msg": "⚙️ prime | رافعة x50 | مخاطرة 5% | مراكز 1 | مسح 300 عملة | أوامر taker",
      "level": "info"
    },
    {
      "time": "2026-07-06 12:25:05 UTC",
      "msg": "مراكز مفتوحة: 1/1 — لا دخول جديد",
      "level": "info"
    },
    {
      "time": "2026-07-06 12:25:05 UTC",
      "msg": "📉 رأس المال الكلي: $0.13 | القمّة $10.66 | تراجع 98.8% | مُنظّم ×0.00",
      "level": "info"
    },
    {
      "time": "2026-07-06 12:25:05 UTC",
      "msg": "💰 الرصيد: $0.0060 USDT",
      "level": "info"
    },
    {
      "time": "2026-07-06 12:25:05 UTC",
      "msg": "⚙️ prime | رافعة x50 | مخاطرة 5% | مراكز 1 | مسح 300 عملة | أوامر taker",
      "level": "info"
    },
    {
      "time": "2026-07-06 12:24:50 UTC",
      "msg": "مراكز مفتوحة: 1/1 — لا دخول جديد",
      "level": "info"
    },
    {
      "time": "2026-07-06 12:24:50 UTC",
      "msg": "📉 رأس المال الكلي: $0.13 | القمّة $10.66 | تراجع 98.8% | مُنظّم ×0.00",
      "level": "info"
    },
    {
      "time": "2026-07-06 12:24:49 UTC",
      "msg": "💰 الرصيد: $0.0060 USDT",
      "level": "info"
    },
    {
      "time": "2026-07-06 12:24:49 UTC",
      "msg": "⚙️ prime | رافعة x50 | مخاطرة 5% | مراكز 1 | مسح 300 عملة | أوامر taker",
      "level": "info"
    }
  ],
  "risk_mode": "prime",
  "top_signals": [],
  "peaks": {},
  "equity_peak": 10.6567,
  "drawdown": 98.77,
  "brain_stats": {
    "wins": 32,
    "losses": 69,
    "total_closed": 101,
    "win_rate": 31.7,
    "weights": {
      "EMA": 0.792,
      "RSI": 1.084,
      "MACD": 0.8,
      "BB": 1.036,
      "Stoch": 1.012,
      "Volume": 0.983,
      "Pattern": 0.873,
      "HTF_1h": 0.768,
      "OBV": 0.889,
      "RSIDivergence": 0.964
    },
    "kelly": 5.0,
    "updated": "2026-07-06 12:29:30 UTC"
  }
}