{
  "last_run": "2026-07-05 23:04:38 UTC",
  "mode": "Live 💰",
  "balance": 0.1839,
  "positions": [
    {
      "instId": "NEAR-USDT-SWAP",
      "side": "بيع 📉",
      "entry": 2.038,
      "size": 0.8,
      "pnl": 0.096
    }
  ],
  "total_trades": 238,
  "logs": [
    {
      "time": "2026-07-05 23:04:38 UTC",
      "msg": "مراكز مفتوحة: 1/1 — لا دخول جديد",
      "level": "info"
    },
    {
      "time": "2026-07-05 23:04:38 UTC",
      "msg": "📉 رأس المال الكلي: $0.73 | القمّة $10.66 | تراجع 93.2% | مُنظّم ×0.00",
      "level": "info"
    },
    {
      "time": "2026-07-05 23:04:38 UTC",
      "msg": "💰 الرصيد: $0.1839 USDT",
      "level": "info"
    },
    {
      "time": "2026-07-05 23:04:38 UTC",
      "msg": "⚙️ prime | رافعة x30 | مخاطرة 5% | مراكز 1 | مسح 300 عملة | أوامر taker",
      "level": "info"
    },
    {
      "time": "2026-07-05 23:04:23 UTC",
      "msg": "مراكز مفتوحة: 1/1 — لا دخول جديد",
      "level": "info"
    },
    {
      "time": "2026-07-05 23:04:22 UTC",
      "msg": "📉 رأس المال الكلي: $0.73 | القمّة $10.66 | تراجع 93.2% | مُنظّم ×0.00",
      "level": "info"
    },
    {
      "time": "2026-07-05 23:04:22 UTC",
      "msg": "💰 الرصيد: $0.1839 USDT",
      "level": "info"
    },
    {
      "time": "2026-07-05 23:04:22 UTC",
      "msg": "⚙️ prime | رافعة x30 | مخاطرة 5% | مراكز 1 | مسح 300 عملة | أوامر taker",
      "level": "info"
    },
    {
      "time": "2026-07-05 23:04:07 UTC",
      "msg": "مراكز مفتوحة: 1/1 — لا دخول جديد",
      "level": "info"
    },
    {
      "time": "2026-07-05 23:04:07 UTC",
      "msg": "📉 رأس المال الكلي: $0.72 | القمّة $10.66 | تراجع 93.3% | مُنظّم ×0.00",
      "level": "info"
    },
    {
      "time": "2026-07-05 23:04:07 UTC",
      "msg": "💰 الرصيد: $0.1757 USDT",
      "level": "info"
    },
    {
      "time": "2026-07-05 23:04:06 UTC",
      "msg": "⚙️ prime | رافعة x30 | مخاطرة 5% | مراكز 1 | مسح 300 عملة | أوامر taker",
      "level": "info"
    },
    {
      "time": "2026-07-05 23:03:51 UTC",
      "msg": "مراكز مفتوحة: 1/1 — لا دخول جديد",
      "level": "info"
    },
    {
      "time": "2026-07-05 23:03:51 UTC",
      "msg": "📉 رأس المال الكلي: $0.72 | القمّة $10.66 | تراجع 93.3% | مُنظّم ×0.00",
      "level": "info"
    },
    {
      "time": "2026-07-05 23:03:51 UTC",
      "msg": "💰 الرصيد: $0.1757 USDT",
      "level": "info"
    },
    {
      "time": "2026-07-05 23:03:51 UTC",
      "msg": "⚙️ prime | رافعة x30 | مخاطرة 5% | مراكز 1 | مسح 300 عملة | أوامر taker",
      "level": "info"
    },
    {
      "time": "2026-07-05 23:03:36 UTC",
      "msg": "مراكز مفتوحة: 1/1 — لا دخول جديد",
      "level": "info"
    },
    {
      "time": "2026-07-05 23:03:36 UTC",
      "msg": "📉 رأس المال الكلي: $0.72 | القمّة $10.66 | تراجع 93.3% | مُنظّم ×0.00",
      "level": "info"
    },
    {
      "time": "2026-07-05 23:03:35 UTC",
      "msg": "💰 الرصيد: $0.1757 USDT",
      "level": "info"
    },
    {
      "time": "2026-07-05 23:03:35 UTC",
      "msg": "⚙️ prime | رافعة x30 | مخاطرة 5% | مراكز 1 | مسح 300 عملة | أوامر taker",
      "level": "info"
    },
    {
      "time": "2026-07-05 23:03:20 UTC",
      "msg": "مراكز مفتوحة: 1/1 — لا دخول جديد",
      "level": "info"
    },
    {
      "time": "2026-07-05 23:03:20 UTC",
      "msg": "📉 رأس المال الكلي: $0.71 | القمّة $10.66 | تراجع 93.3% | مُنظّم ×0.00",
      "level": "info"
    },
    {
      "time": "2026-07-05 23:03:20 UTC",
      "msg": "💰 الرصيد: $0.1674 USDT",
      "level": "info"
    },
    {
      "time": "2026-07-05 23:03:20 UTC",
      "msg": "⚙️ prime | رافعة x30 | مخاطرة 5% | مراكز 1 | مسح 300 عملة | أوامر taker",
      "level": "info"
    },
    {
      "time": "2026-07-05 23:03:05 UTC",
      "msg": "مراكز مفتوحة: 1/1 — لا دخول جديد",
      "level": "info"
    },
    {
      "time": "2026-07-05 23:03:04 UTC",
      "msg": "📉 رأس المال الكلي: $0.72 | القمّة $10.66 | تراجع 93.3% | مُنظّم ×0.00",
      "level": "info"
    },
    {
      "time": "2026-07-05 23:03:04 UTC",
      "msg": "💰 الرصيد: $0.1757 USDT",
      "level": "info"
    },
    {
      "time": "2026-07-05 23:03:04 UTC",
      "msg": "⚙️ prime | رافعة x30 | مخاطرة 5% | مراكز 1 | مسح 300 عملة | أوامر taker",
      "level": "info"
    },
    {
      "time": "2026-07-05 23:02:49 UTC",
      "msg": "مراكز مفتوحة: 1/1 — لا دخول جديد",
      "level": "info"
    },
    {
      "time": "2026-07-05 23:02:49 UTC",
      "msg": "📉 رأس المال الكلي: $0.72 | القمّة $10.66 | تراجع 93.3% | مُنظّم ×0.00",
      "level": "info"
    },
    {
      "time": "2026-07-05 23:02:49 UTC",
      "msg": "💰 الرصيد: $0.1757 USDT",
      "level": "info"
    },
    {
      "time": "2026-07-05 23:02:48 UTC",
      "msg": "⚙️ prime | رافعة x30 | مخاطرة 5% | مراكز 1 | مسح 300 عملة | أوامر taker",
      "level": "info"
    },
    {
      "time": "2026-07-05 23:02:33 UTC",
      "msg": "مراكز مفتوحة: 1/1 — لا دخول جديد",
      "level": "info"
    },
    {
      "time": "2026-07-05 23:02:33 UTC",
      "msg": "📉 رأس المال الكلي: $0.73 | القمّة $10.66 | تراجع 93.2% | مُنظّم ×0.00",
      "level": "info"
    },
    {
      "time": "2026-07-05 23:02:33 UTC",
      "msg": "💰 الرصيد: $0.1839 USDT",
      "level": "info"
    },
    {
      "time": "2026-07-05 23:02:33 UTC",
      "msg": "⚙️ prime | رافعة x30 | مخاطرة 5% | مراكز 1 | مسح 300 عملة | أوامر taker",
      "level": "info"
    },
    {
      "time": "2026-07-05 23:02:18 UTC",
      "msg": "مراكز مفتوحة: 1/1 — لا دخول جديد",
      "level": "info"
    },
    {
      "time": "2026-07-05 23:02:18 UTC",
      "msg": "📉 رأس المال الكلي: $0.73 | القمّة $10.66 | تراجع 93.2% | مُنظّم ×0.00",
      "level": "info"
    },
    {
      "time": "2026-07-05 23:02:17 UTC",
      "msg": "💰 الرصيد: $0.1839 USDT",
      "level": "info"
    },
    {
      "time": "2026-07-05 23:02:17 UTC",
      "msg": "⚙️ prime | رافعة x30 | مخاطرة 5% | مراكز 1 | مسح 300 عملة | أوامر taker",
      "level": "info"
    },
    {
      "time": "2026-07-05 23:02:02 UTC",
      "msg": "مراكز مفتوحة: 1/1 — لا دخول جديد",
      "level": "info"
    },
    {
      "time": "2026-07-05 23:02:02 UTC",
      "msg": "📉 رأس المال الكلي: $0.73 | القمّة $10.66 | تراجع 93.2% | مُنظّم ×0.00",
      "level": "info"
    },
    {
      "time": "2026-07-05 23:02:02 UTC",
      "msg": "💰 الرصيد: $0.1839 USDT",
      "level": "info"
    },
    {
      "time": "2026-07-05 23:02:02 UTC",
      "msg": "⚙️ prime | رافعة x30 | مخاطرة 5% | مراكز 1 | مسح 300 عملة | أوامر taker",
      "level": "info"
    },
    {
      "time": "2026-07-05 23:01:47 UTC",
      "msg": "مراكز مفتوحة: 1/1 — لا دخول جديد",
      "level": "info"
    },
    {
      "time": "2026-07-05 23:01:46 UTC",
      "msg": "📉 رأس المال الكلي: $0.72 | القمّة $10.66 | تراجع 93.3% | مُنظّم ×0.00",
      "level": "info"
    },
    {
      "time": "2026-07-05 23:01:46 UTC",
      "msg": "💰 الرصيد: $0.1757 USDT",
      "level": "info"
    },
    {
      "time": "2026-07-05 23:01:46 UTC",
      "msg": "⚙️ prime | رافعة x30 | مخاطرة 5% | مراكز 1 | مسح 300 عملة | أوامر taker",
      "level": "info"
    },
    {
      "time": "2026-07-05 23:01:31 UTC",
      "msg": "مراكز مفتوحة: 1/1 — لا دخول جديد",
      "level": "info"
    },
    {
      "time": "2026-07-05 23:01:31 UTC",
      "msg": "📉 رأس المال الكلي: $0.72 | القمّة $10.66 | تراجع 93.3% | مُنظّم ×0.00",
      "level": "info"
    },
    {
      "time": "2026-07-05 23:01:31 UTC",
      "msg": "💰 الرصيد: $0.1757 USDT",
      "level": "info"
    },
    {
      "time": "2026-07-05 23:01:30 UTC",
      "msg": "⚙️ prime | رافعة x30 | مخاطرة 5% | مراكز 1 | مسح 300 عملة | أوامر taker",
      "level": "info"
    },
    {
      "time": "2026-07-05 23:01:15 UTC",
      "msg": "مراكز مفتوحة: 1/1 — لا دخول جديد",
      "level": "info"
    },
    {
      "time": "2026-07-05 23:01:15 UTC",
      "msg": "📉 رأس المال الكلي: $0.73 | القمّة $10.66 | تراجع 93.2% | مُنظّم ×0.00",
      "level": "info"
    },
    {
      "time": "2026-07-05 23:01:15 UTC",
      "msg": "💰 الرصيد: $0.1839 USDT",
      "level": "info"
    },
    {
      "time": "2026-07-05 23:01:15 UTC",
      "msg": "⚙️ prime | رافعة x30 | مخاطرة 5% | مراكز 1 | مسح 300 عملة | أوامر taker",
      "level": "info"
    },
    {
      "time": "2026-07-05 23:01:00 UTC",
      "msg": "مراكز مفتوحة: 1/1 — لا دخول جديد",
      "level": "info"
    },
    {
      "time": "2026-07-05 23:01:00 UTC",
      "msg": "📉 رأس المال الكلي: $0.73 | القمّة $10.66 | تراجع 93.1% | مُنظّم ×0.00",
      "level": "info"
    },
    {
      "time": "2026-07-05 23:00:59 UTC",
      "msg": "💰 الرصيد: $0.1922 USDT",
      "level": "info"
    },
    {
      "time": "2026-07-05 23:00:59 UTC",
      "msg": "⚙️ prime | رافعة x30 | مخاطرة 5% | مراكز 1 | مسح 300 عملة | أوامر taker",
      "level": "info"
    },
    {
      "time": "2026-07-05 23:00:44 UTC",
      "msg": "مراكز مفتوحة: 1/1 — لا دخول جديد",
      "level": "info"
    },
    {
      "time": "2026-07-05 23:00:44 UTC",
      "msg": "📉 رأس المال الكلي: $0.73 | القمّة $10.66 | تراجع 93.1% | مُنظّم ×0.00",
      "level": "info"
    },
    {
      "time": "2026-07-05 23:00:44 UTC",
      "msg": "💰 الرصيد: $0.1922 USDT",
      "level": "info"
    },
    {
      "time": "2026-07-05 23:00:44 UTC",
      "msg": "⚙️ prime | رافعة x30 | مخاطرة 5% | مراكز 1 | مسح 300 عملة | أوامر taker",
      "level": "info"
    },
    {
      "time": "2026-07-05 23:00:29 UTC",
      "msg": "مراكز مفتوحة: 1/1 — لا دخول جديد",
      "level": "info"
    },
    {
      "time": "2026-07-05 23:00:28 UTC",
      "msg": "📉 رأس المال الكلي: $0.73 | القمّة $10.66 | تراجع 93.2% | مُنظّم ×0.00",
      "level": "info"
    },
    {
      "time": "2026-07-05 23:00:28 UTC",
      "msg": "💰 الرصيد: $0.1839 USDT",
      "level": "info"
    },
    {
      "time": "2026-07-05 23:00:28 UTC",
      "msg": "⚙️ prime | رافعة x30 | مخاطرة 5% | مراكز 1 | مسح 300 عملة | أوامر taker",
      "level": "info"
    },
    {
      "time": "2026-07-05 23:00:13 UTC",
      "msg": "مراكز مفتوحة: 1/1 — لا دخول جديد",
      "level": "info"
    },
    {
      "time": "2026-07-05 23:00:13 UTC",
      "msg": "📉 رأس المال الكلي: $0.73 | القمّة $10.66 | تراجع 93.2% | مُنظّم ×0.00",
      "level": "info"
    },
    {
      "time": "2026-07-05 23:00:13 UTC",
      "msg": "💰 الرصيد: $0.1839 USDT",
      "level": "info"
    },
    {
      "time": "2026-07-05 23:00:12 UTC",
      "msg": "⚙️ prime | رافعة x30 | مخاطرة 5% | مراكز 1 | مسح 300 عملة | أوامر taker",
      "level": "info"
    },
    {
      "time": "2026-07-05 22:59:57 UTC",
      "msg": "مراكز مفتوحة: 1/1 — لا دخول جديد",
      "level": "info"
    },
    {
      "time": "2026-07-05 22:59:57 UTC",
      "msg": "📉 رأس المال الكلي: $0.72 | القمّة $10.66 | تراجع 93.3% | مُنظّم ×0.00",
      "level": "info"
    },
    {
      "time": "2026-07-05 22:59:57 UTC",
      "msg": "💰 الرصيد: $0.1757 USDT",
      "level": "info"
    },
    {
      "time": "2026-07-05 22:59:57 UTC",
      "msg": "⚙️ prime | رافعة x30 | مخاطرة 5% | مراكز 1 | مسح 300 عملة | أوامر taker",
      "level": "info"
    },
    {
      "time": "2026-07-05 22:59:42 UTC",
      "msg": "مراكز مفتوحة: 1/1 — لا دخول جديد",
      "level": "info"
    },
    {
      "time": "2026-07-05 22:59:42 UTC",
      "msg": "📉 رأس المال الكلي: $0.71 | القمّة $10.66 | تراجع 93.3% | مُنظّم ×0.00",
      "level": "info"
    },
    {
      "time": "2026-07-05 22:59:41 UTC",
      "msg": "💰 الرصيد: $0.1674 USDT",
      "level": "info"
    },
    {
      "time": "2026-07-05 22:59:41 UTC",
      "msg": "⚙️ prime | رافعة x30 | مخاطرة 5% | مراكز 1 | مسح 300 عملة | أوامر taker",
      "level": "info"
    }
  ],
  "risk_mode": "prime",
  "top_signals": [
    {
      "instId": "DATA-USDT-SWAP",
      "signal": "buy",
      "score": 42,
      "prob": 0.65
    },
    {
      "instId": "NEAR-USDT-SWAP",
      "signal": "buy",
      "score": 45,
      "prob": 0.65
    },
    {
      "instId": "PIPPIN-USDT-SWAP",
      "signal": "buy",
      "score": 45,
      "prob": 0.65
    },
    {
      "instId": "AI-USDT-SWAP",
      "signal": "buy",
      "score": 38,
      "prob": 0.63
    }
  ],
  "peaks": {},
  "equity_peak": 10.6567,
  "drawdown": 93.2,
  "brain_stats": {
    "wins": 31,
    "losses": 64,
    "total_closed": 95,
    "win_rate": 32.6,
    "weights": {
      "EMA": 0.777,
      "RSI": 1.09,
      "MACD": 0.782,
      "BB": 1.041,
      "Stoch": 1.012,
      "Volume": 0.983,
      "Pattern": 0.882,
      "HTF_1h": 0.751,
      "OBV": 0.878,
      "RSIDivergence": 0.964
    },
    "kelly": 5.1,
    "updated": "2026-07-05 23:04:23 UTC"
  }
}