{
  "last_run": "2026-06-27 19:57:13 UTC",
  "mode": "Live 💰",
  "balance": 0.3469,
  "positions": [
    {
      "instId": "HYPE-USDT-SWAP",
      "side": "بيع 📉",
      "entry": 62.455,
      "size": 11.0,
      "pnl": 0.2552
    }
  ],
  "total_trades": 167,
  "logs": [
    {
      "time": "2026-06-27 19:57:14 UTC",
      "msg": "مراكز مفتوحة: 1/1 — لا دخول جديد",
      "level": "info"
    },
    {
      "time": "2026-06-27 19:57:14 UTC",
      "msg": "📉 رأس المال الكلي: $1.71 | القمّة $13.21 | تراجع 87.0% | مُنظّم ×0.00",
      "level": "info"
    },
    {
      "time": "2026-06-27 19:57:13 UTC",
      "msg": "💰 الرصيد: $0.3469 USDT",
      "level": "info"
    },
    {
      "time": "2026-06-27 19:57:13 UTC",
      "msg": "⚙️ rocket | رافعة أقصى/عملة | مخاطرة 5% | مراكز 1 | مسح 100 عملة | أوامر taker",
      "level": "info"
    },
    {
      "time": "2026-06-27 19:57:13 UTC",
      "msg": "الوضع: Live 💰",
      "level": "info"
    },
    {
      "time": "2026-06-27 19:57:13 UTC",
      "msg": "🚀 تشغيل Snowball v22 + Brain...",
      "level": "success"
    },
    {
      "time": "2026-06-27 19:57:10 UTC",
      "msg": "مراكز مفتوحة: 1/1 — لا دخول جديد",
      "level": "info"
    },
    {
      "time": "2026-06-27 19:57:10 UTC",
      "msg": "📉 رأس المال الكلي: $1.72 | القمّة $13.21 | تراجع 87.0% | مُنظّم ×0.00",
      "level": "info"
    },
    {
      "time": "2026-06-27 19:57:10 UTC",
      "msg": "💰 الرصيد: $0.3480 USDT",
      "level": "info"
    },
    {
      "time": "2026-06-27 19:57:09 UTC",
      "msg": "⚙️ rocket | رافعة أقصى/عملة | مخاطرة 5% | مراكز 1 | مسح 100 عملة | أوامر taker",
      "level": "info"
    },
    {
      "time": "2026-06-27 19:57:09 UTC",
      "msg": "الوضع: Live 💰",
      "level": "info"
    },
    {
      "time": "2026-06-27 19:57:09 UTC",
      "msg": "🚀 تشغيل Snowball v22 + Brain...",
      "level": "success"
    },
    {
      "time": "2026-06-27 19:56:56 UTC",
      "msg": "مراكز مفتوحة: 1/1 — لا دخول جديد",
      "level": "info"
    },
    {
      "time": "2026-06-27 19:56:55 UTC",
      "msg": "📉 رأس المال الكلي: $1.72 | القمّة $13.21 | تراجع 87.0% | مُنظّم ×0.00",
      "level": "info"
    },
    {
      "time": "2026-06-27 19:56:55 UTC",
      "msg": "💰 الرصيد: $0.3559 USDT",
      "level": "info"
    },
    {
      "time": "2026-06-27 19:56:55 UTC",
      "msg": "⚙️ rocket | رافعة أقصى/عملة | مخاطرة 5% | مراكز 1 | مسح 100 عملة | أوامر taker",
      "level": "info"
    },
    {
      "time": "2026-06-27 19:56:55 UTC",
      "msg": "الوضع: Live 💰",
      "level": "info"
    },
    {
      "time": "2026-06-27 19:56:55 UTC",
      "msg": "🚀 تشغيل Snowball v22 + Brain...",
      "level": "success"
    },
    {
      "time": "2026-06-27 19:56:17 UTC",
      "msg": "مراكز مفتوحة: 1/1 — لا دخول جديد",
      "level": "info"
    },
    {
      "time": "2026-06-27 19:56:17 UTC",
      "msg": "📉 رأس المال الكلي: $1.71 | القمّة $13.21 | تراجع 87.0% | مُنظّم ×0.00",
      "level": "info"
    },
    {
      "time": "2026-06-27 19:56:17 UTC",
      "msg": "💰 الرصيد: $0.3458 USDT",
      "level": "info"
    },
    {
      "time": "2026-06-27 19:56:16 UTC",
      "msg": "⚙️ rocket | رافعة أقصى/عملة | مخاطرة 5% | مراكز 1 | مسح 100 عملة | أوامر taker",
      "level": "info"
    },
    {
      "time": "2026-06-27 19:56:16 UTC",
      "msg": "الوضع: Live 💰",
      "level": "info"
    },
    {
      "time": "2026-06-27 19:56:16 UTC",
      "msg": "🚀 تشغيل Snowball v22 + Brain...",
      "level": "success"
    },
    {
      "time": "2026-06-27 19:56:06 UTC",
      "msg": "مراكز مفتوحة: 1/1 — لا دخول جديد",
      "level": "info"
    },
    {
      "time": "2026-06-27 19:56:06 UTC",
      "msg": "📉 رأس المال الكلي: $1.67 | القمّة $13.21 | تراجع 87.3% | مُنظّم ×0.00",
      "level": "info"
    },
    {
      "time": "2026-06-27 19:56:06 UTC",
      "msg": "💰 الرصيد: $0.3009 USDT",
      "level": "info"
    },
    {
      "time": "2026-06-27 19:56:06 UTC",
      "msg": "⚙️ rocket | رافعة أقصى/عملة | مخاطرة 5% | مراكز 1 | مسح 100 عملة | أوامر taker",
      "level": "info"
    },
    {
      "time": "2026-06-27 19:56:05 UTC",
      "msg": "الوضع: Live 💰",
      "level": "info"
    },
    {
      "time": "2026-06-27 19:56:05 UTC",
      "msg": "🚀 تشغيل Snowball v22 + Brain...",
      "level": "success"
    },
    {
      "time": "2026-06-27 19:55:59 UTC",
      "msg": "مراكز مفتوحة: 1/1 — لا دخول جديد",
      "level": "info"
    },
    {
      "time": "2026-06-27 19:55:59 UTC",
      "msg": "📉 رأس المال الكلي: $1.75 | القمّة $13.21 | تراجع 86.8% | مُنظّم ×0.00",
      "level": "info"
    },
    {
      "time": "2026-06-27 19:55:59 UTC",
      "msg": "💰 الرصيد: $0.3828 USDT",
      "level": "info"
    },
    {
      "time": "2026-06-27 19:55:58 UTC",
      "msg": "⚙️ rocket | رافعة أقصى/عملة | مخاطرة 5% | مراكز 1 | مسح 100 عملة | أوامر taker",
      "level": "info"
    },
    {
      "time": "2026-06-27 19:55:58 UTC",
      "msg": "الوضع: Live 💰",
      "level": "info"
    },
    {
      "time": "2026-06-27 19:55:58 UTC",
      "msg": "🚀 تشغيل Snowball v22 + Brain...",
      "level": "success"
    },
    {
      "time": "2026-06-27 19:55:55 UTC",
      "msg": "مراكز مفتوحة: 1/1 — لا دخول جديد",
      "level": "info"
    },
    {
      "time": "2026-06-27 19:55:55 UTC",
      "msg": "📉 رأس المال الكلي: $1.73 | القمّة $13.21 | تراجع 86.9% | مُنظّم ×0.00",
      "level": "info"
    },
    {
      "time": "2026-06-27 19:55:54 UTC",
      "msg": "💰 الرصيد: $0.3436 USDT",
      "level": "info"
    },
    {
      "time": "2026-06-27 19:55:54 UTC",
      "msg": "⚙️ rocket | رافعة أقصى/عملة | مخاطرة 5% | مراكز 1 | مسح 100 عملة | أوامر taker",
      "level": "info"
    },
    {
      "time": "2026-06-27 19:55:54 UTC",
      "msg": "الوضع: Live 💰",
      "level": "info"
    },
    {
      "time": "2026-06-27 19:55:54 UTC",
      "msg": "🚀 تشغيل Snowball v22 + Brain...",
      "level": "success"
    },
    {
      "time": "2026-06-27 19:55:42 UTC",
      "msg": "مراكز مفتوحة: 1/1 — لا دخول جديد",
      "level": "info"
    },
    {
      "time": "2026-06-27 19:55:41 UTC",
      "msg": "📉 رأس المال الكلي: $1.62 | القمّة $13.21 | تراجع 87.7% | مُنظّم ×0.00",
      "level": "info"
    },
    {
      "time": "2026-06-27 19:55:41 UTC",
      "msg": "💰 الرصيد: $0.2493 USDT",
      "level": "info"
    },
    {
      "time": "2026-06-27 19:55:41 UTC",
      "msg": "⚙️ rocket | رافعة أقصى/عملة | مخاطرة 5% | مراكز 1 | مسح 100 عملة | أوامر taker",
      "level": "info"
    },
    {
      "time": "2026-06-27 19:55:41 UTC",
      "msg": "الوضع: Live 💰",
      "level": "info"
    },
    {
      "time": "2026-06-27 19:55:41 UTC",
      "msg": "🚀 تشغيل Snowball v22 + Brain...",
      "level": "success"
    },
    {
      "time": "2026-06-27 19:55:04 UTC",
      "msg": "مراكز مفتوحة: 1/1 — لا دخول جديد",
      "level": "info"
    },
    {
      "time": "2026-06-27 19:55:04 UTC",
      "msg": "📉 رأس المال الكلي: $1.56 | القمّة $13.21 | تراجع 88.2% | مُنظّم ×0.00",
      "level": "info"
    },
    {
      "time": "2026-06-27 19:55:03 UTC",
      "msg": "💰 الرصيد: $0.1854 USDT",
      "level": "info"
    },
    {
      "time": "2026-06-27 19:55:03 UTC",
      "msg": "⚙️ rocket | رافعة أقصى/عملة | مخاطرة 5% | مراكز 1 | مسح 100 عملة | أوامر taker",
      "level": "info"
    },
    {
      "time": "2026-06-27 19:55:03 UTC",
      "msg": "الوضع: Live 💰",
      "level": "info"
    },
    {
      "time": "2026-06-27 19:55:03 UTC",
      "msg": "🚀 تشغيل Snowball v22 + Brain...",
      "level": "success"
    },
    {
      "time": "2026-06-27 19:54:52 UTC",
      "msg": "مراكز مفتوحة: 1/1 — لا دخول جديد",
      "level": "info"
    },
    {
      "time": "2026-06-27 19:54:52 UTC",
      "msg": "📉 رأس المال الكلي: $1.53 | القمّة $13.21 | تراجع 88.4% | مُنظّم ×0.00",
      "level": "info"
    },
    {
      "time": "2026-06-27 19:54:52 UTC",
      "msg": "💰 الرصيد: $0.1551 USDT",
      "level": "info"
    },
    {
      "time": "2026-06-27 19:54:51 UTC",
      "msg": "⚙️ rocket | رافعة أقصى/عملة | مخاطرة 5% | مراكز 1 | مسح 100 عملة | أوامر taker",
      "level": "info"
    },
    {
      "time": "2026-06-27 19:54:51 UTC",
      "msg": "الوضع: Live 💰",
      "level": "info"
    },
    {
      "time": "2026-06-27 19:54:51 UTC",
      "msg": "🚀 تشغيل Snowball v22 + Brain...",
      "level": "success"
    },
    {
      "time": "2026-06-27 19:54:40 UTC",
      "msg": "مراكز مفتوحة: 1/1 — لا دخول جديد",
      "level": "info"
    },
    {
      "time": "2026-06-27 19:54:39 UTC",
      "msg": "📉 رأس المال الكلي: $1.49 | القمّة $13.21 | تراجع 88.7% | مُنظّم ×0.00",
      "level": "info"
    },
    {
      "time": "2026-06-27 19:54:39 UTC",
      "msg": "💰 الرصيد: $0.1192 USDT",
      "level": "info"
    },
    {
      "time": "2026-06-27 19:54:39 UTC",
      "msg": "⚙️ rocket | رافعة أقصى/عملة | مخاطرة 5% | مراكز 1 | مسح 100 عملة | أوامر taker",
      "level": "info"
    },
    {
      "time": "2026-06-27 19:54:38 UTC",
      "msg": "الوضع: Live 💰",
      "level": "info"
    },
    {
      "time": "2026-06-27 19:54:38 UTC",
      "msg": "🚀 تشغيل Snowball v22 + Brain...",
      "level": "success"
    },
    {
      "time": "2026-06-27 19:54:37 UTC",
      "msg": "مراكز مفتوحة: 1/1 — لا دخول جديد",
      "level": "info"
    },
    {
      "time": "2026-06-27 19:54:36 UTC",
      "msg": "📉 رأس المال الكلي: $1.49 | القمّة $13.21 | تراجع 88.7% | مُنظّم ×0.00",
      "level": "info"
    },
    {
      "time": "2026-06-27 19:54:36 UTC",
      "msg": "💰 الرصيد: $0.1180 USDT",
      "level": "info"
    },
    {
      "time": "2026-06-27 19:54:36 UTC",
      "msg": "⚙️ rocket | رافعة أقصى/عملة | مخاطرة 5% | مراكز 1 | مسح 100 عملة | أوامر taker",
      "level": "info"
    },
    {
      "time": "2026-06-27 19:54:36 UTC",
      "msg": "الوضع: Live 💰",
      "level": "info"
    },
    {
      "time": "2026-06-27 19:54:36 UTC",
      "msg": "🚀 تشغيل Snowball v22 + Brain...",
      "level": "success"
    },
    {
      "time": "2026-06-27 19:54:29 UTC",
      "msg": "مراكز مفتوحة: 1/1 — لا دخول جديد",
      "level": "info"
    },
    {
      "time": "2026-06-27 19:54:29 UTC",
      "msg": "📉 رأس المال الكلي: $1.48 | القمّة $13.21 | تراجع 88.8% | مُنظّم ×0.00",
      "level": "info"
    },
    {
      "time": "2026-06-27 19:54:29 UTC",
      "msg": "💰 الرصيد: $0.1057 USDT",
      "level": "info"
    },
    {
      "time": "2026-06-27 19:54:28 UTC",
      "msg": "⚙️ rocket | رافعة أقصى/عملة | مخاطرة 5% | مراكز 1 | مسح 100 عملة | أوامر taker",
      "level": "info"
    },
    {
      "time": "2026-06-27 19:54:28 UTC",
      "msg": "الوضع: Live 💰",
      "level": "info"
    },
    {
      "time": "2026-06-27 19:54:28 UTC",
      "msg": "🚀 تشغيل Snowball v22 + Brain...",
      "level": "success"
    },
    {
      "time": "2026-06-27 19:53:51 UTC",
      "msg": "مراكز مفتوحة: 1/1 — لا دخول جديد",
      "level": "info"
    },
    {
      "time": "2026-06-27 19:53:51 UTC",
      "msg": "📉 رأس المال الكلي: $1.47 | القمّة $13.21 | تراجع 88.8% | مُنظّم ×0.00",
      "level": "info"
    }
  ],
  "risk_mode": "rocket",
  "top_signals": [
    {
      "instId": "XAU-USDT-SWAP",
      "signal": "sell",
      "score": -56,
      "prob": 0.28
    },
    {
      "instId": "WIF-USDT-SWAP",
      "signal": "sell",
      "score": -45,
      "prob": 0.31
    },
    {
      "instId": "XRP-USDT-SWAP",
      "signal": "sell",
      "score": -42,
      "prob": 0.33
    },
    {
      "instId": "PUMP-USDT-SWAP",
      "signal": "sell",
      "score": -42,
      "prob": 0.34
    },
    {
      "instId": "HYPE-USDT-SWAP",
      "signal": "sell",
      "score": -35,
      "prob": 0.36
    }
  ],
  "peaks": {
    "DOT-USDT-SWAP": -0.0149326962049612
  },
  "pnl_peaks": {
    "DOT-USDT-SWAP": -0.0419999999999945
  },
  "brain_stats": {
    "wins": 17,
    "losses": 36,
    "total_closed": 53,
    "win_rate": 32.1,
    "weights": {
      "EMA": 0.779,
      "RSI": 1.049,
      "MACD": 0.822,
      "BB": 1.033,
      "Stoch": 0.996,
      "Volume": 0.981,
      "Pattern": 0.898,
      "HTF_1h": 0.745,
      "OBV": 0.844,
      "RSIDivergence": 0.994
    },
    "kelly": 5.0,
    "updated": "2026-06-27 19:57:10 UTC"
  },
  "equity_peak": 13.2074,
  "drawdown": 87.03
}