{
  "last_run": "2026-07-05 17:26:46 UTC",
  "mode": "Live 💰",
  "balance": 0.6109,
  "positions": [
    {
      "instId": "DOGE-USDT-SWAP",
      "side": "شراء 📈",
      "entry": 0.07644,
      "size": 0.45,
      "pnl": 0.5175
    }
  ],
  "total_trades": 231,
  "logs": [
    {
      "time": "2026-07-05 17:26:47 UTC",
      "msg": "مراكز مفتوحة: 1/1 — لا دخول جديد",
      "level": "info"
    },
    {
      "time": "2026-07-05 17:26:47 UTC",
      "msg": "📉 رأس المال الكلي: $1.77 | القمّة $10.66 | تراجع 83.3% | مُنظّم ×0.00",
      "level": "info"
    },
    {
      "time": "2026-07-05 17:26:47 UTC",
      "msg": "💰 الرصيد: $0.6109 USDT",
      "level": "info"
    },
    {
      "time": "2026-07-05 17:26:46 UTC",
      "msg": "⚙️ prime | رافعة x30 | مخاطرة 5% | مراكز 1 | مسح 100 عملة | أوامر taker",
      "level": "info"
    },
    {
      "time": "2026-07-05 17:26:31 UTC",
      "msg": "مراكز مفتوحة: 1/1 — لا دخول جديد",
      "level": "info"
    },
    {
      "time": "2026-07-05 17:26:31 UTC",
      "msg": "📉 رأس المال الكلي: $1.77 | القمّة $10.66 | تراجع 83.4% | مُنظّم ×0.00",
      "level": "info"
    },
    {
      "time": "2026-07-05 17:26:31 UTC",
      "msg": "💰 الرصيد: $0.6066 USDT",
      "level": "info"
    },
    {
      "time": "2026-07-05 17:26:31 UTC",
      "msg": "⚙️ prime | رافعة x30 | مخاطرة 5% | مراكز 1 | مسح 100 عملة | أوامر taker",
      "level": "info"
    },
    {
      "time": "2026-07-05 17:26:16 UTC",
      "msg": "مراكز مفتوحة: 1/1 — لا دخول جديد",
      "level": "info"
    },
    {
      "time": "2026-07-05 17:26:15 UTC",
      "msg": "📉 رأس المال الكلي: $1.77 | القمّة $10.66 | تراجع 83.4% | مُنظّم ×0.00",
      "level": "info"
    },
    {
      "time": "2026-07-05 17:26:15 UTC",
      "msg": "💰 الرصيد: $0.6066 USDT",
      "level": "info"
    },
    {
      "time": "2026-07-05 17:26:15 UTC",
      "msg": "⚙️ prime | رافعة x30 | مخاطرة 5% | مراكز 1 | مسح 100 عملة | أوامر taker",
      "level": "info"
    },
    {
      "time": "2026-07-05 17:26:00 UTC",
      "msg": "مراكز مفتوحة: 1/1 — لا دخول جديد",
      "level": "info"
    },
    {
      "time": "2026-07-05 17:25:59 UTC",
      "msg": "📉 رأس المال الكلي: $1.78 | القمّة $10.66 | تراجع 83.3% | مُنظّم ×0.00",
      "level": "info"
    },
    {
      "time": "2026-07-05 17:25:59 UTC",
      "msg": "💰 الرصيد: $0.6196 USDT",
      "level": "info"
    },
    {
      "time": "2026-07-05 17:25:59 UTC",
      "msg": "⚙️ prime | رافعة x30 | مخاطرة 5% | مراكز 1 | مسح 100 عملة | أوامر taker",
      "level": "info"
    },
    {
      "time": "2026-07-05 17:25:44 UTC",
      "msg": "مراكز مفتوحة: 1/1 — لا دخول جديد",
      "level": "info"
    },
    {
      "time": "2026-07-05 17:25:44 UTC",
      "msg": "📉 رأس المال الكلي: $1.79 | القمّة $10.66 | تراجع 83.2% | مُنظّم ×0.00",
      "level": "info"
    },
    {
      "time": "2026-07-05 17:25:43 UTC",
      "msg": "💰 الرصيد: $0.6283 USDT",
      "level": "info"
    },
    {
      "time": "2026-07-05 17:25:43 UTC",
      "msg": "⚙️ prime | رافعة x30 | مخاطرة 5% | مراكز 1 | مسح 100 عملة | أوامر taker",
      "level": "info"
    },
    {
      "time": "2026-07-05 17:25:28 UTC",
      "msg": "مراكز مفتوحة: 1/1 — لا دخول جديد",
      "level": "info"
    },
    {
      "time": "2026-07-05 17:25:28 UTC",
      "msg": "📉 رأس المال الكلي: $1.79 | القمّة $10.66 | تراجع 83.2% | مُنظّم ×0.00",
      "level": "info"
    },
    {
      "time": "2026-07-05 17:25:27 UTC",
      "msg": "💰 الرصيد: $0.6153 USDT",
      "level": "info"
    },
    {
      "time": "2026-07-05 17:25:27 UTC",
      "msg": "⚙️ prime | رافعة x30 | مخاطرة 5% | مراكز 1 | مسح 100 عملة | أوامر taker",
      "level": "info"
    },
    {
      "time": "2026-07-05 17:25:12 UTC",
      "msg": "مراكز مفتوحة: 1/1 — لا دخول جديد",
      "level": "info"
    },
    {
      "time": "2026-07-05 17:25:12 UTC",
      "msg": "📉 رأس المال الكلي: $1.85 | القمّة $10.66 | تراجع 82.6% | مُنظّم ×0.00",
      "level": "info"
    },
    {
      "time": "2026-07-05 17:25:12 UTC",
      "msg": "💰 الرصيد: $0.6849 USDT",
      "level": "info"
    },
    {
      "time": "2026-07-05 17:25:11 UTC",
      "msg": "⚙️ prime | رافعة x30 | مخاطرة 5% | مراكز 1 | مسح 100 عملة | أوامر taker",
      "level": "info"
    },
    {
      "time": "2026-07-05 17:24:56 UTC",
      "msg": "مراكز مفتوحة: 1/1 — لا دخول جديد",
      "level": "info"
    },
    {
      "time": "2026-07-05 17:24:56 UTC",
      "msg": "📉 رأس المال الكلي: $1.88 | القمّة $10.66 | تراجع 82.4% | مُنظّم ×0.00",
      "level": "info"
    },
    {
      "time": "2026-07-05 17:24:56 UTC",
      "msg": "💰 الرصيد: $0.7110 USDT",
      "level": "info"
    },
    {
      "time": "2026-07-05 17:24:55 UTC",
      "msg": "⚙️ prime | رافعة x30 | مخاطرة 5% | مراكز 1 | مسح 100 عملة | أوامر taker",
      "level": "info"
    },
    {
      "time": "2026-07-05 17:24:40 UTC",
      "msg": "مراكز مفتوحة: 1/1 — لا دخول جديد",
      "level": "info"
    },
    {
      "time": "2026-07-05 17:24:40 UTC",
      "msg": "📉 رأس المال الكلي: $1.87 | القمّة $10.66 | تراجع 82.5% | مُنظّم ×0.00",
      "level": "info"
    },
    {
      "time": "2026-07-05 17:24:40 UTC",
      "msg": "💰 الرصيد: $0.7066 USDT",
      "level": "info"
    },
    {
      "time": "2026-07-05 17:24:40 UTC",
      "msg": "⚙️ prime | رافعة x30 | مخاطرة 5% | مراكز 1 | مسح 100 عملة | أوامر taker",
      "level": "info"
    },
    {
      "time": "2026-07-05 17:24:25 UTC",
      "msg": "مراكز مفتوحة: 1/1 — لا دخول جديد",
      "level": "info"
    },
    {
      "time": "2026-07-05 17:24:24 UTC",
      "msg": "📉 رأس المال الكلي: $1.86 | القمّة $10.66 | تراجع 82.5% | مُنظّم ×0.00",
      "level": "info"
    },
    {
      "time": "2026-07-05 17:24:24 UTC",
      "msg": "💰 الرصيد: $0.6936 USDT",
      "level": "info"
    },
    {
      "time": "2026-07-05 17:24:24 UTC",
      "msg": "⚙️ prime | رافعة x30 | مخاطرة 5% | مراكز 1 | مسح 100 عملة | أوامر taker",
      "level": "info"
    },
    {
      "time": "2026-07-05 17:24:09 UTC",
      "msg": "مراكز مفتوحة: 1/1 — لا دخول جديد",
      "level": "info"
    },
    {
      "time": "2026-07-05 17:24:09 UTC",
      "msg": "📉 رأس المال الكلي: $1.84 | القمّة $10.66 | تراجع 82.7% | مُنظّم ×0.00",
      "level": "info"
    },
    {
      "time": "2026-07-05 17:24:08 UTC",
      "msg": "💰 الرصيد: $0.6762 USDT",
      "level": "info"
    },
    {
      "time": "2026-07-05 17:24:08 UTC",
      "msg": "⚙️ prime | رافعة x30 | مخاطرة 5% | مراكز 1 | مسح 100 عملة | أوامر taker",
      "level": "info"
    },
    {
      "time": "2026-07-05 17:23:53 UTC",
      "msg": "مراكز مفتوحة: 1/1 — لا دخول جديد",
      "level": "info"
    },
    {
      "time": "2026-07-05 17:23:53 UTC",
      "msg": "📉 رأس المال الكلي: $1.85 | القمّة $10.66 | تراجع 82.6% | مُنظّم ×0.00",
      "level": "info"
    },
    {
      "time": "2026-07-05 17:23:52 UTC",
      "msg": "💰 الرصيد: $0.6805 USDT",
      "level": "info"
    },
    {
      "time": "2026-07-05 17:23:52 UTC",
      "msg": "⚙️ prime | رافعة x30 | مخاطرة 5% | مراكز 1 | مسح 100 عملة | أوامر taker",
      "level": "info"
    },
    {
      "time": "2026-07-05 17:23:37 UTC",
      "msg": "مراكز مفتوحة: 1/1 — لا دخول جديد",
      "level": "info"
    },
    {
      "time": "2026-07-05 17:23:37 UTC",
      "msg": "📉 رأس المال الكلي: $1.82 | القمّة $10.66 | تراجع 82.9% | مُنظّم ×0.00",
      "level": "info"
    },
    {
      "time": "2026-07-05 17:23:37 UTC",
      "msg": "💰 الرصيد: $0.6544 USDT",
      "level": "info"
    },
    {
      "time": "2026-07-05 17:23:36 UTC",
      "msg": "⚙️ prime | رافعة x30 | مخاطرة 5% | مراكز 1 | مسح 100 عملة | أوامر taker",
      "level": "info"
    },
    {
      "time": "2026-07-05 17:23:21 UTC",
      "msg": "مراكز مفتوحة: 1/1 — لا دخول جديد",
      "level": "info"
    },
    {
      "time": "2026-07-05 17:23:21 UTC",
      "msg": "📉 رأس المال الكلي: $1.82 | القمّة $10.66 | تراجع 82.9% | مُنظّم ×0.00",
      "level": "info"
    },
    {
      "time": "2026-07-05 17:23:21 UTC",
      "msg": "💰 الرصيد: $0.6588 USDT",
      "level": "info"
    },
    {
      "time": "2026-07-05 17:23:20 UTC",
      "msg": "⚙️ prime | رافعة x30 | مخاطرة 5% | مراكز 1 | مسح 100 عملة | أوامر taker",
      "level": "info"
    },
    {
      "time": "2026-07-05 17:23:05 UTC",
      "msg": "مراكز مفتوحة: 1/1 — لا دخول جديد",
      "level": "info"
    },
    {
      "time": "2026-07-05 17:23:05 UTC",
      "msg": "📉 رأس المال الكلي: $1.83 | القمّة $10.66 | تراجع 82.8% | مُنظّم ×0.00",
      "level": "info"
    },
    {
      "time": "2026-07-05 17:23:05 UTC",
      "msg": "💰 الرصيد: $0.6675 USDT",
      "level": "info"
    },
    {
      "time": "2026-07-05 17:23:05 UTC",
      "msg": "⚙️ prime | رافعة x30 | مخاطرة 5% | مراكز 1 | مسح 100 عملة | أوامر taker",
      "level": "info"
    },
    {
      "time": "2026-07-05 17:22:50 UTC",
      "msg": "مراكز مفتوحة: 1/1 — لا دخول جديد",
      "level": "info"
    },
    {
      "time": "2026-07-05 17:22:49 UTC",
      "msg": "📉 رأس المال الكلي: $1.69 | القمّة $10.66 | تراجع 84.2% | مُنظّم ×0.00",
      "level": "info"
    },
    {
      "time": "2026-07-05 17:22:49 UTC",
      "msg": "💰 الرصيد: $0.5283 USDT",
      "level": "info"
    },
    {
      "time": "2026-07-05 17:22:49 UTC",
      "msg": "⚙️ prime | رافعة x30 | مخاطرة 5% | مراكز 1 | مسح 100 عملة | أوامر taker",
      "level": "info"
    },
    {
      "time": "2026-07-05 17:22:34 UTC",
      "msg": "مراكز مفتوحة: 1/1 — لا دخول جديد",
      "level": "info"
    },
    {
      "time": "2026-07-05 17:22:34 UTC",
      "msg": "📉 رأس المال الكلي: $1.63 | القمّة $10.66 | تراجع 84.7% | مُنظّم ×0.00",
      "level": "info"
    },
    {
      "time": "2026-07-05 17:22:33 UTC",
      "msg": "💰 الرصيد: $0.4674 USDT",
      "level": "info"
    },
    {
      "time": "2026-07-05 17:22:33 UTC",
      "msg": "⚙️ prime | رافعة x30 | مخاطرة 5% | مراكز 1 | مسح 100 عملة | أوامر taker",
      "level": "info"
    },
    {
      "time": "2026-07-05 17:22:18 UTC",
      "msg": "مراكز مفتوحة: 1/1 — لا دخول جديد",
      "level": "info"
    },
    {
      "time": "2026-07-05 17:22:18 UTC",
      "msg": "📉 رأس المال الكلي: $1.63 | القمّة $10.66 | تراجع 84.7% | مُنظّم ×0.00",
      "level": "info"
    },
    {
      "time": "2026-07-05 17:22:17 UTC",
      "msg": "💰 الرصيد: $0.4674 USDT",
      "level": "info"
    },
    {
      "time": "2026-07-05 17:22:17 UTC",
      "msg": "⚙️ prime | رافعة x30 | مخاطرة 5% | مراكز 1 | مسح 100 عملة | أوامر taker",
      "level": "info"
    },
    {
      "time": "2026-07-05 17:22:02 UTC",
      "msg": "مراكز مفتوحة: 1/1 — لا دخول جديد",
      "level": "info"
    },
    {
      "time": "2026-07-05 17:22:02 UTC",
      "msg": "📉 رأس المال الكلي: $1.63 | القمّة $10.66 | تراجع 84.7% | مُنظّم ×0.00",
      "level": "info"
    },
    {
      "time": "2026-07-05 17:22:02 UTC",
      "msg": "💰 الرصيد: $0.4674 USDT",
      "level": "info"
    },
    {
      "time": "2026-07-05 17:22:01 UTC",
      "msg": "⚙️ prime | رافعة x30 | مخاطرة 5% | مراكز 1 | مسح 100 عملة | أوامر taker",
      "level": "info"
    },
    {
      "time": "2026-07-05 17:21:46 UTC",
      "msg": "مراكز مفتوحة: 1/1 — لا دخول جديد",
      "level": "info"
    },
    {
      "time": "2026-07-05 17:21:46 UTC",
      "msg": "📉 رأس المال الكلي: $1.63 | القمّة $10.66 | تراجع 84.7% | مُنظّم ×0.00",
      "level": "info"
    },
    {
      "time": "2026-07-05 17:21:46 UTC",
      "msg": "💰 الرصيد: $0.4717 USDT",
      "level": "info"
    },
    {
      "time": "2026-07-05 17:21:45 UTC",
      "msg": "⚙️ prime | رافعة x30 | مخاطرة 5% | مراكز 1 | مسح 100 عملة | أوامر taker",
      "level": "info"
    }
  ],
  "risk_mode": "prime",
  "top_signals": [],
  "peaks": {},
  "equity_peak": 10.6567,
  "drawdown": 83.35,
  "brain_stats": {
    "wins": 28,
    "losses": 60,
    "total_closed": 88,
    "win_rate": 31.8,
    "weights": {
      "EMA": 0.783,
      "RSI": 1.081,
      "MACD": 0.799,
      "BB": 1.042,
      "Stoch": 1.001,
      "Volume": 0.978,
      "Pattern": 0.897,
      "HTF_1h": 0.757,
      "OBV": 0.87,
      "RSIDivergence": 0.964
    },
    "kelly": 5.0,
    "updated": "2026-07-05 17:26:31 UTC"
  }
}