{
  "last_run": "2026-06-24 04:44:56 UTC",
  "mode": "Live 💰",
  "balance": 6.6373,
  "positions": [],
  "total_trades": 4,
  "logs": [
    {
      "time": "2026-06-24 04:44:56 UTC",
      "msg": "🛑 البوت متوقف — 0 صفقة مغلقة: لا يوجد",
      "level": "warning"
    },
    {
      "time": "2026-06-24 04:44:56 UTC",
      "msg": "🛑 bot_stop.json — إيقاف طارئ: إغلاق جميع الصفقات",
      "level": "warning"
    },
    {
      "time": "2026-06-24 04:44:48 UTC",
      "msg": "🛑 البوت متوقف — 0 صفقة مغلقة: لا يوجد",
      "level": "warning"
    },
    {
      "time": "2026-06-24 04:44:47 UTC",
      "msg": "🛑 bot_stop.json — إيقاف طارئ: إغلاق جميع الصفقات",
      "level": "warning"
    },
    {
      "time": "2026-06-24 04:44:40 UTC",
      "msg": "🛑 البوت متوقف — 0 صفقة مغلقة: لا يوجد",
      "level": "warning"
    },
    {
      "time": "2026-06-24 04:44:39 UTC",
      "msg": "🛑 bot_stop.json — إيقاف طارئ: إغلاق جميع الصفقات",
      "level": "warning"
    },
    {
      "time": "2026-06-24 04:44:26 UTC",
      "msg": "🛑 البوت متوقف — 0 صفقة مغلقة: لا يوجد",
      "level": "warning"
    },
    {
      "time": "2026-06-24 04:44:25 UTC",
      "msg": "🛑 bot_stop.json — إيقاف طارئ: إغلاق جميع الصفقات",
      "level": "warning"
    },
    {
      "time": "2026-06-24 04:44:22 UTC",
      "msg": "🛑 البوت متوقف — 0 صفقة مغلقة: لا يوجد",
      "level": "warning"
    },
    {
      "time": "2026-06-24 04:44:21 UTC",
      "msg": "🛑 bot_stop.json — إيقاف طارئ: إغلاق جميع الصفقات",
      "level": "warning"
    },
    {
      "time": "2026-06-24 04:43:37 UTC",
      "msg": "🛑 البوت متوقف — 0 صفقة مغلقة: لا يوجد",
      "level": "warning"
    },
    {
      "time": "2026-06-24 04:43:36 UTC",
      "msg": "🛑 bot_stop.json — إيقاف طارئ: إغلاق جميع الصفقات",
      "level": "warning"
    },
    {
      "time": "2026-06-24 04:43:24 UTC",
      "msg": "🛑 البوت متوقف — 0 صفقة مغلقة: لا يوجد",
      "level": "warning"
    },
    {
      "time": "2026-06-24 04:43:23 UTC",
      "msg": "🛑 bot_stop.json — إيقاف طارئ: إغلاق جميع الصفقات",
      "level": "warning"
    },
    {
      "time": "2026-06-24 04:43:18 UTC",
      "msg": "🛑 البوت متوقف — 0 صفقة مغلقة: لا يوجد",
      "level": "warning"
    },
    {
      "time": "2026-06-24 04:43:18 UTC",
      "msg": "🛑 bot_stop.json — إيقاف طارئ: إغلاق جميع الصفقات",
      "level": "warning"
    },
    {
      "time": "2026-06-24 04:43:15 UTC",
      "msg": "🛑 البوت متوقف — 0 صفقة مغلقة: لا يوجد",
      "level": "warning"
    },
    {
      "time": "2026-06-24 04:43:15 UTC",
      "msg": "🛑 bot_stop.json — إيقاف طارئ: إغلاق جميع الصفقات",
      "level": "warning"
    },
    {
      "time": "2026-06-24 04:43:05 UTC",
      "msg": "🛑 البوت متوقف — 0 صفقة مغلقة: لا يوجد",
      "level": "warning"
    },
    {
      "time": "2026-06-24 04:43:05 UTC",
      "msg": "🛑 bot_stop.json — إيقاف طارئ: إغلاق جميع الصفقات",
      "level": "warning"
    },
    {
      "time": "2026-06-24 04:42:59 UTC",
      "msg": "🛑 البوت متوقف — 0 صفقة مغلقة: لا يوجد",
      "level": "warning"
    },
    {
      "time": "2026-06-24 04:42:58 UTC",
      "msg": "🛑 bot_stop.json — إيقاف طارئ: إغلاق جميع الصفقات",
      "level": "warning"
    },
    {
      "time": "2026-06-24 04:42:54 UTC",
      "msg": "🛑 البوت متوقف — 0 صفقة مغلقة: لا يوجد",
      "level": "warning"
    },
    {
      "time": "2026-06-24 04:42:53 UTC",
      "msg": "🛑 bot_stop.json — إيقاف طارئ: إغلاق جميع الصفقات",
      "level": "warning"
    },
    {
      "time": "2026-06-24 04:42:50 UTC",
      "msg": "🛑 البوت متوقف — 0 صفقة مغلقة: لا يوجد",
      "level": "warning"
    },
    {
      "time": "2026-06-24 04:42:49 UTC",
      "msg": "🛑 bot_stop.json — إيقاف طارئ: إغلاق جميع الصفقات",
      "level": "warning"
    },
    {
      "time": "2026-06-24 04:42:42 UTC",
      "msg": "🛑 البوت متوقف — 0 صفقة مغلقة: لا يوجد",
      "level": "warning"
    },
    {
      "time": "2026-06-24 04:42:41 UTC",
      "msg": "🛑 bot_stop.json — إيقاف طارئ: إغلاق جميع الصفقات",
      "level": "warning"
    },
    {
      "time": "2026-06-24 04:42:39 UTC",
      "msg": "🛑 البوت متوقف — 0 صفقة مغلقة: لا يوجد",
      "level": "warning"
    },
    {
      "time": "2026-06-24 04:42:39 UTC",
      "msg": "🛑 bot_stop.json — إيقاف طارئ: إغلاق جميع الصفقات",
      "level": "warning"
    },
    {
      "time": "2026-06-24 04:42:34 UTC",
      "msg": "🛑 البوت متوقف — 0 صفقة مغلقة: لا يوجد",
      "level": "warning"
    },
    {
      "time": "2026-06-24 04:42:33 UTC",
      "msg": "🛑 bot_stop.json — إيقاف طارئ: إغلاق جميع الصفقات",
      "level": "warning"
    },
    {
      "time": "2026-06-24 04:41:53 UTC",
      "msg": "🛑 البوت متوقف — 0 صفقة مغلقة: لا يوجد",
      "level": "warning"
    },
    {
      "time": "2026-06-24 04:41:52 UTC",
      "msg": "🛑 bot_stop.json — إيقاف طارئ: إغلاق جميع الصفقات",
      "level": "warning"
    },
    {
      "time": "2026-06-24 04:41:39 UTC",
      "msg": "🛑 البوت متوقف — 0 صفقة مغلقة: لا يوجد",
      "level": "warning"
    },
    {
      "time": "2026-06-24 04:41:38 UTC",
      "msg": "🛑 bot_stop.json — إيقاف طارئ: إغلاق جميع الصفقات",
      "level": "warning"
    },
    {
      "time": "2026-06-24 04:41:35 UTC",
      "msg": "🛑 البوت متوقف — 0 صفقة مغلقة: لا يوجد",
      "level": "warning"
    },
    {
      "time": "2026-06-24 04:41:34 UTC",
      "msg": "🛑 bot_stop.json — إيقاف طارئ: إغلاق جميع الصفقات",
      "level": "warning"
    },
    {
      "time": "2026-06-24 04:41:32 UTC",
      "msg": "🛑 البوت متوقف — 0 صفقة مغلقة: لا يوجد",
      "level": "warning"
    },
    {
      "time": "2026-06-24 04:41:31 UTC",
      "msg": "🛑 bot_stop.json — إيقاف طارئ: إغلاق جميع الصفقات",
      "level": "warning"
    },
    {
      "time": "2026-06-24 04:41:16 UTC",
      "msg": "🛑 البوت متوقف — 0 صفقة مغلقة: لا يوجد",
      "level": "warning"
    },
    {
      "time": "2026-06-24 04:41:16 UTC",
      "msg": "🛑 bot_stop.json — إيقاف طارئ: إغلاق جميع الصفقات",
      "level": "warning"
    },
    {
      "time": "2026-06-24 04:41:12 UTC",
      "msg": "🛑 البوت متوقف — 0 صفقة مغلقة: لا يوجد",
      "level": "warning"
    },
    {
      "time": "2026-06-24 04:41:11 UTC",
      "msg": "🛑 bot_stop.json — إيقاف طارئ: إغلاق جميع الصفقات",
      "level": "warning"
    },
    {
      "time": "2026-06-24 04:41:03 UTC",
      "msg": "🛑 البوت متوقف — 0 صفقة مغلقة: لا يوجد",
      "level": "warning"
    },
    {
      "time": "2026-06-24 04:41:02 UTC",
      "msg": "🛑 bot_stop.json — إيقاف طارئ: إغلاق جميع الصفقات",
      "level": "warning"
    },
    {
      "time": "2026-06-24 04:41:01 UTC",
      "msg": "🛑 البوت متوقف — 0 صفقة مغلقة: لا يوجد",
      "level": "warning"
    },
    {
      "time": "2026-06-24 04:41:00 UTC",
      "msg": "🛑 bot_stop.json — إيقاف طارئ: إغلاق جميع الصفقات",
      "level": "warning"
    },
    {
      "time": "2026-06-24 04:40:58 UTC",
      "msg": "🛑 البوت متوقف — 0 صفقة مغلقة: لا يوجد",
      "level": "warning"
    },
    {
      "time": "2026-06-24 04:40:57 UTC",
      "msg": "🛑 bot_stop.json — إيقاف طارئ: إغلاق جميع الصفقات",
      "level": "warning"
    },
    {
      "time": "2026-06-24 04:40:50 UTC",
      "msg": "🛑 البوت متوقف — 0 صفقة مغلقة: لا يوجد",
      "level": "warning"
    },
    {
      "time": "2026-06-24 04:40:50 UTC",
      "msg": "🛑 bot_stop.json — إيقاف طارئ: إغلاق جميع الصفقات",
      "level": "warning"
    },
    {
      "time": "2026-06-24 04:40:00 UTC",
      "msg": "🛑 البوت متوقف — 0 صفقة مغلقة: لا يوجد",
      "level": "warning"
    },
    {
      "time": "2026-06-24 04:40:00 UTC",
      "msg": "🛑 bot_stop.json — إيقاف طارئ: إغلاق جميع الصفقات",
      "level": "warning"
    },
    {
      "time": "2026-06-24 04:39:53 UTC",
      "msg": "🛑 البوت متوقف — 0 صفقة مغلقة: لا يوجد",
      "level": "warning"
    },
    {
      "time": "2026-06-24 04:39:53 UTC",
      "msg": "🛑 bot_stop.json — إيقاف طارئ: إغلاق جميع الصفقات",
      "level": "warning"
    },
    {
      "time": "2026-06-24 04:39:49 UTC",
      "msg": "🛑 البوت متوقف — 0 صفقة مغلقة: لا يوجد",
      "level": "warning"
    },
    {
      "time": "2026-06-24 04:39:48 UTC",
      "msg": "🛑 bot_stop.json — إيقاف طارئ: إغلاق جميع الصفقات",
      "level": "warning"
    },
    {
      "time": "2026-06-24 04:39:46 UTC",
      "msg": "🛑 البوت متوقف — 0 صفقة مغلقة: لا يوجد",
      "level": "warning"
    },
    {
      "time": "2026-06-24 04:39:46 UTC",
      "msg": "🛑 bot_stop.json — إيقاف طارئ: إغلاق جميع الصفقات",
      "level": "warning"
    },
    {
      "time": "2026-06-24 04:39:33 UTC",
      "msg": "🛑 البوت متوقف — 0 صفقة مغلقة: لا يوجد",
      "level": "warning"
    },
    {
      "time": "2026-06-24 04:39:32 UTC",
      "msg": "🛑 bot_stop.json — إيقاف طارئ: إغلاق جميع الصفقات",
      "level": "warning"
    },
    {
      "time": "2026-06-24 04:39:28 UTC",
      "msg": "🛑 البوت متوقف — 0 صفقة مغلقة: لا يوجد",
      "level": "warning"
    },
    {
      "time": "2026-06-24 04:39:27 UTC",
      "msg": "🛑 bot_stop.json — إيقاف طارئ: إغلاق جميع الصفقات",
      "level": "warning"
    },
    {
      "time": "2026-06-24 04:39:22 UTC",
      "msg": "🛑 البوت متوقف — 0 صفقة مغلقة: لا يوجد",
      "level": "warning"
    },
    {
      "time": "2026-06-24 04:39:21 UTC",
      "msg": "🛑 bot_stop.json — إيقاف طارئ: إغلاق جميع الصفقات",
      "level": "warning"
    },
    {
      "time": "2026-06-24 04:39:17 UTC",
      "msg": "🛑 البوت متوقف — 0 صفقة مغلقة: لا يوجد",
      "level": "warning"
    },
    {
      "time": "2026-06-24 04:39:17 UTC",
      "msg": "🛑 bot_stop.json — إيقاف طارئ: إغلاق جميع الصفقات",
      "level": "warning"
    },
    {
      "time": "2026-06-24 04:39:15 UTC",
      "msg": "🛑 البوت متوقف — 0 صفقة مغلقة: لا يوجد",
      "level": "warning"
    },
    {
      "time": "2026-06-24 04:39:15 UTC",
      "msg": "🛑 bot_stop.json — إيقاف طارئ: إغلاق جميع الصفقات",
      "level": "warning"
    },
    {
      "time": "2026-06-24 04:39:12 UTC",
      "msg": "🛑 البوت متوقف — 0 صفقة مغلقة: لا يوجد",
      "level": "warning"
    },
    {
      "time": "2026-06-24 04:39:12 UTC",
      "msg": "🛑 bot_stop.json — إيقاف طارئ: إغلاق جميع الصفقات",
      "level": "warning"
    },
    {
      "time": "2026-06-24 04:38:58 UTC",
      "msg": "🛑 البوت متوقف — 0 صفقة مغلقة: لا يوجد",
      "level": "warning"
    },
    {
      "time": "2026-06-24 04:38:57 UTC",
      "msg": "🛑 bot_stop.json — إيقاف طارئ: إغلاق جميع الصفقات",
      "level": "warning"
    },
    {
      "time": "2026-06-24 04:38:21 UTC",
      "msg": "🛑 البوت متوقف — 0 صفقة مغلقة: لا يوجد",
      "level": "warning"
    },
    {
      "time": "2026-06-24 04:38:21 UTC",
      "msg": "🛑 bot_stop.json — إيقاف طارئ: إغلاق جميع الصفقات",
      "level": "warning"
    },
    {
      "time": "2026-06-24 04:38:07 UTC",
      "msg": "🛑 البوت متوقف — 0 صفقة مغلقة: لا يوجد",
      "level": "warning"
    },
    {
      "time": "2026-06-24 04:38:07 UTC",
      "msg": "🛑 bot_stop.json — إيقاف طارئ: إغلاق جميع الصفقات",
      "level": "warning"
    },
    {
      "time": "2026-06-24 04:38:03 UTC",
      "msg": "🛑 البوت متوقف — 0 صفقة مغلقة: لا يوجد",
      "level": "warning"
    },
    {
      "time": "2026-06-24 04:38:02 UTC",
      "msg": "🛑 bot_stop.json — إيقاف طارئ: إغلاق جميع الصفقات",
      "level": "warning"
    }
  ],
  "risk_mode": "balanced",
  "top_signals": [
    {
      "instId": "JTO-USDT-SWAP",
      "signal": "buy",
      "score": 42,
      "prob": 0.7
    }
  ],
  "peaks": {
    "KITE-USDT-SWAP": 0.1995946692869865,
    "SLX-USDT-SWAP": 1.690618791420735,
    "JTO-USDT-SWAP": 0.2090447493675907
  },
  "stopped": true
}