{
  "last_run": "2026-07-05 15:04:40 UTC",
  "mode": "Live 💰",
  "balance": 0.4547,
  "positions": [
    {
      "instId": "DOGE-USDT-SWAP",
      "side": "شراء 📈",
      "entry": 0.07644,
      "size": 0.45,
      "pnl": 0.3555
    }
  ],
  "total_trades": 231,
  "logs": [
    {
      "time": "2026-07-05 15:04:40 UTC",
      "msg": "مراكز مفتوحة: 1/1 — لا دخول جديد",
      "level": "info"
    },
    {
      "time": "2026-07-05 15:04:40 UTC",
      "msg": "📉 رأس المال الكلي: $1.61 | القمّة $10.66 | تراجع 84.9% | مُنظّم ×0.00",
      "level": "info"
    },
    {
      "time": "2026-07-05 15:04:40 UTC",
      "msg": "💰 الرصيد: $0.4547 USDT",
      "level": "info"
    },
    {
      "time": "2026-07-05 15:04:40 UTC",
      "msg": "⚙️ prime | رافعة x30 | مخاطرة 5% | مراكز 1 | مسح 100 عملة | أوامر taker",
      "level": "info"
    },
    {
      "time": "2026-07-05 15:04:25 UTC",
      "msg": "مراكز مفتوحة: 1/1 — لا دخول جديد",
      "level": "info"
    },
    {
      "time": "2026-07-05 15:04:24 UTC",
      "msg": "📉 رأس المال الكلي: $1.58 | القمّة $10.66 | تراجع 85.2% | مُنظّم ×0.00",
      "level": "info"
    },
    {
      "time": "2026-07-05 15:04:24 UTC",
      "msg": "💰 الرصيد: $0.4242 USDT",
      "level": "info"
    },
    {
      "time": "2026-07-05 15:04:24 UTC",
      "msg": "⚙️ prime | رافعة x30 | مخاطرة 5% | مراكز 1 | مسح 100 عملة | أوامر taker",
      "level": "info"
    },
    {
      "time": "2026-07-05 15:04:09 UTC",
      "msg": "مراكز مفتوحة: 1/1 — لا دخول جديد",
      "level": "info"
    },
    {
      "time": "2026-07-05 15:04:09 UTC",
      "msg": "📉 رأس المال الكلي: $1.59 | القمّة $10.66 | تراجع 85.1% | مُنظّم ×0.00",
      "level": "info"
    },
    {
      "time": "2026-07-05 15:04:08 UTC",
      "msg": "💰 الرصيد: $0.4329 USDT",
      "level": "info"
    },
    {
      "time": "2026-07-05 15:04:08 UTC",
      "msg": "⚙️ prime | رافعة x30 | مخاطرة 5% | مراكز 1 | مسح 100 عملة | أوامر taker",
      "level": "info"
    },
    {
      "time": "2026-07-05 15:03:53 UTC",
      "msg": "مراكز مفتوحة: 1/1 — لا دخول جديد",
      "level": "info"
    },
    {
      "time": "2026-07-05 15:03:53 UTC",
      "msg": "📉 رأس المال الكلي: $1.60 | القمّة $10.66 | تراجع 85.0% | مُنظّم ×0.00",
      "level": "info"
    },
    {
      "time": "2026-07-05 15:03:53 UTC",
      "msg": "💰 الرصيد: $0.4373 USDT",
      "level": "info"
    },
    {
      "time": "2026-07-05 15:03:52 UTC",
      "msg": "⚙️ prime | رافعة x30 | مخاطرة 5% | مراكز 1 | مسح 100 عملة | أوامر taker",
      "level": "info"
    },
    {
      "time": "2026-07-05 15:03:37 UTC",
      "msg": "مراكز مفتوحة: 1/1 — لا دخول جديد",
      "level": "info"
    },
    {
      "time": "2026-07-05 15:03:37 UTC",
      "msg": "📉 رأس المال الكلي: $1.55 | القمّة $10.66 | تراجع 85.5% | مُنظّم ×0.00",
      "level": "info"
    },
    {
      "time": "2026-07-05 15:03:37 UTC",
      "msg": "💰 الرصيد: $0.3894 USDT",
      "level": "info"
    },
    {
      "time": "2026-07-05 15:03:36 UTC",
      "msg": "⚙️ prime | رافعة x30 | مخاطرة 5% | مراكز 1 | مسح 100 عملة | أوامر taker",
      "level": "info"
    },
    {
      "time": "2026-07-05 15:03:21 UTC",
      "msg": "مراكز مفتوحة: 1/1 — لا دخول جديد",
      "level": "info"
    },
    {
      "time": "2026-07-05 15:03:21 UTC",
      "msg": "📉 رأس المال الكلي: $1.51 | القمّة $10.66 | تراجع 85.8% | مُنظّم ×0.00",
      "level": "info"
    },
    {
      "time": "2026-07-05 15:03:21 UTC",
      "msg": "💰 الرصيد: $0.3590 USDT",
      "level": "info"
    },
    {
      "time": "2026-07-05 15:03:21 UTC",
      "msg": "⚙️ prime | رافعة x30 | مخاطرة 5% | مراكز 1 | مسح 100 عملة | أوامر taker",
      "level": "info"
    },
    {
      "time": "2026-07-05 15:03:06 UTC",
      "msg": "مراكز مفتوحة: 1/1 — لا دخول جديد",
      "level": "info"
    },
    {
      "time": "2026-07-05 15:03:05 UTC",
      "msg": "📉 رأس المال الكلي: $1.50 | القمّة $10.66 | تراجع 85.9% | مُنظّم ×0.00",
      "level": "info"
    },
    {
      "time": "2026-07-05 15:03:05 UTC",
      "msg": "💰 الرصيد: $0.3459 USDT",
      "level": "info"
    },
    {
      "time": "2026-07-05 15:03:05 UTC",
      "msg": "⚙️ prime | رافعة x30 | مخاطرة 5% | مراكز 1 | مسح 100 عملة | أوامر taker",
      "level": "info"
    },
    {
      "time": "2026-07-05 15:02:50 UTC",
      "msg": "مراكز مفتوحة: 1/1 — لا دخول جديد",
      "level": "info"
    },
    {
      "time": "2026-07-05 15:02:50 UTC",
      "msg": "📉 رأس المال الكلي: $1.50 | القمّة $10.66 | تراجع 85.9% | مُنظّم ×0.00",
      "level": "info"
    },
    {
      "time": "2026-07-05 15:02:49 UTC",
      "msg": "💰 الرصيد: $0.3459 USDT",
      "level": "info"
    },
    {
      "time": "2026-07-05 15:02:49 UTC",
      "msg": "⚙️ prime | رافعة x30 | مخاطرة 5% | مراكز 1 | مسح 100 عملة | أوامر taker",
      "level": "info"
    },
    {
      "time": "2026-07-05 15:02:34 UTC",
      "msg": "مراكز مفتوحة: 1/1 — لا دخول جديد",
      "level": "info"
    },
    {
      "time": "2026-07-05 15:02:34 UTC",
      "msg": "📉 رأس المال الكلي: $1.51 | القمّة $10.66 | تراجع 85.8% | مُنظّم ×0.00",
      "level": "info"
    },
    {
      "time": "2026-07-05 15:02:34 UTC",
      "msg": "💰 الرصيد: $0.3590 USDT",
      "level": "info"
    },
    {
      "time": "2026-07-05 15:02:33 UTC",
      "msg": "⚙️ prime | رافعة x30 | مخاطرة 5% | مراكز 1 | مسح 100 عملة | أوامر taker",
      "level": "info"
    },
    {
      "time": "2026-07-05 15:02:18 UTC",
      "msg": "مراكز مفتوحة: 1/1 — لا دخول جديد",
      "level": "info"
    },
    {
      "time": "2026-07-05 15:02:18 UTC",
      "msg": "📉 رأس المال الكلي: $1.52 | القمّة $10.66 | تراجع 85.8% | مُنظّم ×0.00",
      "level": "info"
    },
    {
      "time": "2026-07-05 15:02:18 UTC",
      "msg": "💰 الرصيد: $0.3633 USDT",
      "level": "info"
    },
    {
      "time": "2026-07-05 15:02:17 UTC",
      "msg": "⚙️ prime | رافعة x30 | مخاطرة 5% | مراكز 1 | مسح 100 عملة | أوامر taker",
      "level": "info"
    },
    {
      "time": "2026-07-05 15:02:02 UTC",
      "msg": "مراكز مفتوحة: 1/1 — لا دخول جديد",
      "level": "info"
    },
    {
      "time": "2026-07-05 15:02:02 UTC",
      "msg": "📉 رأس المال الكلي: $1.53 | القمّة $10.66 | تراجع 85.6% | مُنظّم ×0.00",
      "level": "info"
    },
    {
      "time": "2026-07-05 15:02:02 UTC",
      "msg": "💰 الرصيد: $0.3764 USDT",
      "level": "info"
    },
    {
      "time": "2026-07-05 15:02:02 UTC",
      "msg": "⚙️ prime | رافعة x30 | مخاطرة 5% | مراكز 1 | مسح 100 عملة | أوامر taker",
      "level": "info"
    },
    {
      "time": "2026-07-05 15:01:47 UTC",
      "msg": "مراكز مفتوحة: 1/1 — لا دخول جديد",
      "level": "info"
    },
    {
      "time": "2026-07-05 15:01:46 UTC",
      "msg": "📉 رأس المال الكلي: $1.53 | القمّة $10.66 | تراجع 85.7% | مُنظّم ×0.00",
      "level": "info"
    },
    {
      "time": "2026-07-05 15:01:46 UTC",
      "msg": "💰 الرصيد: $0.3720 USDT",
      "level": "info"
    },
    {
      "time": "2026-07-05 15:01:46 UTC",
      "msg": "⚙️ prime | رافعة x30 | مخاطرة 5% | مراكز 1 | مسح 100 عملة | أوامر taker",
      "level": "info"
    },
    {
      "time": "2026-07-05 15:01:31 UTC",
      "msg": "مراكز مفتوحة: 1/1 — لا دخول جديد",
      "level": "info"
    },
    {
      "time": "2026-07-05 15:01:31 UTC",
      "msg": "📉 رأس المال الكلي: $1.51 | القمّة $10.66 | تراجع 85.8% | مُنظّم ×0.00",
      "level": "info"
    },
    {
      "time": "2026-07-05 15:01:30 UTC",
      "msg": "💰 الرصيد: $0.3590 USDT",
      "level": "info"
    },
    {
      "time": "2026-07-05 15:01:30 UTC",
      "msg": "⚙️ prime | رافعة x30 | مخاطرة 5% | مراكز 1 | مسح 100 عملة | أوامر taker",
      "level": "info"
    },
    {
      "time": "2026-07-05 15:01:15 UTC",
      "msg": "مراكز مفتوحة: 1/1 — لا دخول جديد",
      "level": "info"
    },
    {
      "time": "2026-07-05 15:01:15 UTC",
      "msg": "📉 رأس المال الكلي: $1.52 | القمّة $10.66 | تراجع 85.7% | مُنظّم ×0.00",
      "level": "info"
    },
    {
      "time": "2026-07-05 15:01:15 UTC",
      "msg": "💰 الرصيد: $0.3677 USDT",
      "level": "info"
    },
    {
      "time": "2026-07-05 15:01:14 UTC",
      "msg": "⚙️ prime | رافعة x30 | مخاطرة 5% | مراكز 1 | مسح 100 عملة | أوامر taker",
      "level": "info"
    },
    {
      "time": "2026-07-05 15:00:59 UTC",
      "msg": "مراكز مفتوحة: 1/1 — لا دخول جديد",
      "level": "info"
    },
    {
      "time": "2026-07-05 15:00:59 UTC",
      "msg": "📉 رأس المال الكلي: $1.51 | القمّة $10.66 | تراجع 85.8% | مُنظّم ×0.00",
      "level": "info"
    },
    {
      "time": "2026-07-05 15:00:59 UTC",
      "msg": "💰 الرصيد: $0.3546 USDT",
      "level": "info"
    },
    {
      "time": "2026-07-05 15:00:58 UTC",
      "msg": "⚙️ prime | رافعة x30 | مخاطرة 5% | مراكز 1 | مسح 100 عملة | أوامر taker",
      "level": "info"
    },
    {
      "time": "2026-07-05 15:00:43 UTC",
      "msg": "مراكز مفتوحة: 1/1 — لا دخول جديد",
      "level": "info"
    },
    {
      "time": "2026-07-05 15:00:43 UTC",
      "msg": "📉 رأس المال الكلي: $1.51 | القمّة $10.66 | تراجع 85.9% | مُنظّم ×0.00",
      "level": "info"
    },
    {
      "time": "2026-07-05 15:00:43 UTC",
      "msg": "💰 الرصيد: $0.3503 USDT",
      "level": "info"
    },
    {
      "time": "2026-07-05 15:00:43 UTC",
      "msg": "⚙️ prime | رافعة x30 | مخاطرة 5% | مراكز 1 | مسح 100 عملة | أوامر taker",
      "level": "info"
    },
    {
      "time": "2026-07-05 15:00:28 UTC",
      "msg": "مراكز مفتوحة: 1/1 — لا دخول جديد",
      "level": "info"
    },
    {
      "time": "2026-07-05 15:00:27 UTC",
      "msg": "📉 رأس المال الكلي: $1.51 | القمّة $10.66 | تراجع 85.9% | مُنظّم ×0.00",
      "level": "info"
    },
    {
      "time": "2026-07-05 15:00:27 UTC",
      "msg": "💰 الرصيد: $0.3503 USDT",
      "level": "info"
    },
    {
      "time": "2026-07-05 15:00:27 UTC",
      "msg": "⚙️ prime | رافعة x30 | مخاطرة 5% | مراكز 1 | مسح 100 عملة | أوامر taker",
      "level": "info"
    },
    {
      "time": "2026-07-05 15:00:12 UTC",
      "msg": "مراكز مفتوحة: 1/1 — لا دخول جديد",
      "level": "info"
    },
    {
      "time": "2026-07-05 15:00:12 UTC",
      "msg": "📉 رأس المال الكلي: $1.52 | القمّة $10.66 | تراجع 85.8% | مُنظّم ×0.00",
      "level": "info"
    },
    {
      "time": "2026-07-05 15:00:11 UTC",
      "msg": "💰 الرصيد: $0.3633 USDT",
      "level": "info"
    },
    {
      "time": "2026-07-05 15:00:11 UTC",
      "msg": "⚙️ prime | رافعة x30 | مخاطرة 5% | مراكز 1 | مسح 100 عملة | أوامر taker",
      "level": "info"
    },
    {
      "time": "2026-07-05 14:59:56 UTC",
      "msg": "مراكز مفتوحة: 1/1 — لا دخول جديد",
      "level": "info"
    },
    {
      "time": "2026-07-05 14:59:56 UTC",
      "msg": "📉 رأس المال الكلي: $1.53 | القمّة $10.66 | تراجع 85.7% | مُنظّم ×0.00",
      "level": "info"
    },
    {
      "time": "2026-07-05 14:59:56 UTC",
      "msg": "💰 الرصيد: $0.3720 USDT",
      "level": "info"
    },
    {
      "time": "2026-07-05 14:59:55 UTC",
      "msg": "⚙️ prime | رافعة x30 | مخاطرة 5% | مراكز 1 | مسح 100 عملة | أوامر taker",
      "level": "info"
    },
    {
      "time": "2026-07-05 14:59:40 UTC",
      "msg": "مراكز مفتوحة: 1/1 — لا دخول جديد",
      "level": "info"
    },
    {
      "time": "2026-07-05 14:59:40 UTC",
      "msg": "📉 رأس المال الكلي: $1.52 | القمّة $10.66 | تراجع 85.8% | مُنظّم ×0.00",
      "level": "info"
    },
    {
      "time": "2026-07-05 14:59:40 UTC",
      "msg": "💰 الرصيد: $0.3633 USDT",
      "level": "info"
    },
    {
      "time": "2026-07-05 14:59:39 UTC",
      "msg": "⚙️ prime | رافعة x30 | مخاطرة 5% | مراكز 1 | مسح 100 عملة | أوامر taker",
      "level": "info"
    }
  ],
  "risk_mode": "prime",
  "top_signals": [],
  "peaks": {},
  "equity_peak": 10.6567,
  "drawdown": 84.86,
  "brain_stats": {
    "wins": 28,
    "losses": 60,
    "total_closed": 88,
    "win_rate": 31.8,
    "weights": {
      "EMA": 0.783,
      "RSI": 1.081,
      "MACD": 0.799,
      "BB": 1.042,
      "Stoch": 1.001,
      "Volume": 0.978,
      "Pattern": 0.897,
      "HTF_1h": 0.757,
      "OBV": 0.87,
      "RSIDivergence": 0.964
    },
    "kelly": 5.0,
    "updated": "2026-07-05 15:04:25 UTC"
  }
}